{"success":false,"errors":{"employee":{"name_mismatch":true,"in_file_to_much":false,"in_file_to_few":false,"from_file":["name","job title","department","employee annual salary","estimated annual salary minus furloughs"],"from_conf":["first name","last name","phone"]},"calendar":{"name_mismatch":true,"in_file_to_much":false,"in_file_to_few":false,"from_file":{"1":"job title","2":"department","3":"employee annual salary","4":"estimated annual salary minus furloughs"},"from_conf":{"1":"last name","2":"address1","3":"address2","4":"address3"}},"cars":{"name_mismatch":true,"in_file_to_much":false,"in_file_to_few":false,"from_file":["name"],"from_conf":["name1"]},"okokok<":{"name_mismatch":true,"in_file_to_much":true,"in_file_to_few":false,"from_file":{"4":"estimated annual salary minus furloughs"},"from_conf":[]},"okokok>":{"name_mismatch":true,"in_file_to_much":false,"in_file_to_few":true,"from_file":[],"from_conf":{"5":"new field"}}},"columns":[{"data":"NAME","type":"text"},{"data":"JOB TITLE","type":"text"},{"data":"DEPARTMENT","type":"text"},{"data":"EMPLOYEE ANNUAL SALARY","type":"text"},{"data":"ESTIMATED ANNUAL SALARY MINUS FURLOUGHS","type":"text"}],"headers":["NAME","JOB TITLE","DEPARTMENT","EMPLOYEE ANNUAL SALARY","ESTIMATED ANNUAL SALARY MINUS FURLOUGHS"],"data":[{"NAME":"AARON, ELVIA J","JOB TITLE":"WATER RATE TAKER","DEPARTMENT":"WATER MGMNT","EMPLOYEE ANNUAL SALARY":"$81000.00","ESTIMATED ANNUAL SALARY MINUS FURLOUGHS":"$73862.00"},{"NAME":"AARON, JEFFERY M","JOB TITLE":"POLICE OFFICER","DEPARTMENT":"POLICE","EMPLOYEE ANNUAL SALARY":"$74628.00","ESTIMATED ANNUAL SALARY MINUS FURLOUGHS":"$74628.00"},{"NAME":"AARON, KIMBERLEI R","JOB TITLE":"CHIEF CONTRACT EXPEDITER","DEPARTMENT":"FLEET MANAGEMNT","EMPLOYEE ANNUAL SALARY":"$77280.00","ESTIMATED ANNUAL SALARY MINUS FURLOUGHS":"$70174.00"},{"NAME":"ABAD JR, VICENTE M","JOB TITLE":"CIVIL ENGINEER IV","DEPARTMENT":"WATER MGMNT","EMPLOYEE ANNUAL SALARY":"$96276.00","ESTIMATED ANNUAL SALARY MINUS FURLOUGHS":"$96276.00"},{"NAME":"ABBATACOLA, ROBERT J","JOB TITLE":"ELECTRICAL MECHANIC","DEPARTMENT":"WATER MGMNT","EMPLOYEE ANNUAL SALARY":"$84032.00","ESTIMATED ANNUAL SALARY MINUS FURLOUGHS":"$76627.00"},{"NAME":"ABBATE, TERRY M","JOB TITLE":"POLICE OFFICER","DEPARTMENT":"POLICE","EMPLOYEE ANNUAL SALARY":"$79926.00","ESTIMATED ANNUAL SALARY MINUS FURLOUGHS":"$79926.00"},{"NAME":"ABBATEMARCO, JAMES J","JOB TITLE":"FIREFIGHTER","DEPARTMENT":"FIRE","EMPLOYEE ANNUAL SALARY":"$77238.00","ESTIMATED ANNUAL SALARY MINUS FURLOUGHS":"$77238.00"},{"NAME":"ABBOTT, BETTY L","JOB TITLE":"FOSTER GRANDPARENT","DEPARTMENT":"FAMILY & SUPPORT","EMPLOYEE ANNUAL SALARY":"$2756.00","ESTIMATED ANNUAL SALARY MINUS FURLOUGHS":"$2756.00"},{"NAME":"ABBOTT, LYNISE M","JOB TITLE":"CLERK III","DEPARTMENT":"FAMILY & SUPPORT","EMPLOYEE ANNUAL SALARY":"$38568.00","ESTIMATED ANNUAL SALARY MINUS FURLOUGHS":"$38568.00"},{"NAME":"ABBOTT, SAM J","JOB TITLE":"ELECTRICAL MECHANIC","DEPARTMENT":"TRANSPORTN","EMPLOYEE ANNUAL SALARY":"$84032.00","ESTIMATED ANNUAL SALARY MINUS FURLOUGHS":"$76627.00"},{"NAME":"ABDELHADI, ABDALMAHD","JOB TITLE":"POLICE OFFICER","DEPARTMENT":"POLICE","EMPLOYEE ANNUAL SALARY":"$71040.00","ESTIMATED ANNUAL SALARY MINUS FURLOUGHS":"$71040.00"},{"NAME":"ABDELLATIF, AREF R","JOB TITLE":"FIREFIGHTER (PER ARBITRATORS AWARD)-PARAMEDIC","DEPARTMENT":"FIRE","EMPLOYEE ANNUAL SALARY":"$86922.00","ESTIMATED ANNUAL SALARY MINUS FURLOUGHS":"$86922.00"},{"NAME":"ABDELMAJEID, AZIZ","JOB TITLE":"POLICE OFFICER","DEPARTMENT":"POLICE","EMPLOYEE ANNUAL SALARY":"$67704.00","ESTIMATED ANNUAL SALARY MINUS FURLOUGHS":"$67704.00"},{"NAME":"ABDOLLAHZADEH, ALI","JOB TITLE":"PARAMEDIC","DEPARTMENT":"FIRE","EMPLOYEE ANNUAL SALARY":"$64374.00","ESTIMATED ANNUAL SALARY MINUS FURLOUGHS":"$64374.00"},{"NAME":"ABDUL-KARIM, MUHAMMAD A","JOB TITLE":"ENGINEERING TECHNICIAN V","DEPARTMENT":"WATER MGMNT","EMPLOYEE ANNUAL SALARY":"$81000.00","ESTIMATED ANNUAL SALARY MINUS FURLOUGHS":"$81000.00"},{"NAME":"ABDULLAH, KEVIN","JOB TITLE":"FIREFIGHTER","DEPARTMENT":"FIRE","EMPLOYEE ANNUAL SALARY":"$83148.00","ESTIMATED ANNUAL SALARY MINUS FURLOUGHS":"$83148.00"},{"NAME":"ABDULLAH, LAKENYA N","JOB TITLE":"CROSSING GUARD","DEPARTMENT":"POLICE","EMPLOYEE ANNUAL SALARY":"$15319.00","ESTIMATED ANNUAL SALARY MINUS FURLOUGHS":"$15319.00"},{"NAME":"ABDULLAH, MOULAY R","JOB TITLE":"POLICE OFFICER","DEPARTMENT":"POLICE","EMPLOYEE ANNUAL SALARY":"$82878.00","ESTIMATED ANNUAL SALARY MINUS FURLOUGHS":"$82878.00"},{"NAME":"ABDULLAH, RASHAD J","JOB TITLE":"ELECTRICAL MECHANIC-AUTO-POLICE MTR MNT","DEPARTMENT":"FLEET MANAGEMNT","EMPLOYEE ANNUAL SALARY":"$84032.00","ESTIMATED ANNUAL SALARY MINUS FURLOUGHS":"$76627.00"},{"NAME":"ABEJERO, JASON V","JOB TITLE":"POLICE OFFICER","DEPARTMENT":"POLICE","EMPLOYEE ANNUAL SALARY":"$77238.00","ESTIMATED ANNUAL SALARY MINUS FURLOUGHS":"$77238.00"},{"NAME":"ABEJERO, RESTITUTO E","JOB TITLE":"POLICE OFFICER","DEPARTMENT":"POLICE","EMPLOYEE ANNUAL SALARY":"$77238.00","ESTIMATED ANNUAL SALARY MINUS FURLOUGHS":"$77238.00"},{"NAME":"ABELS, KENNETH L","JOB TITLE":"SERGEANT","DEPARTMENT":"POLICE","EMPLOYEE ANNUAL SALARY":"$105018.00","ESTIMATED ANNUAL SALARY MINUS FURLOUGHS":"$105018.00"},{"NAME":"ABERCROMBIE, TIMOTHY","JOB TITLE":"MOTOR TRUCK DRIVER","DEPARTMENT":"STREETS & SAN","EMPLOYEE ANNUAL SALARY":"$70408.00","ESTIMATED ANNUAL SALARY MINUS FURLOUGHS":"$70408.00"},{"NAME":"ABNER III, EWART G","JOB TITLE":"LABORER (BUREAU OF ELECTRICITY)","DEPARTMENT":"REVENUE","EMPLOYEE ANNUAL SALARY":"$73216.00","ESTIMATED ANNUAL SALARY MINUS FURLOUGHS":"$66764.00"},{"NAME":"ABOUELKHEIR, HASSAN A","JOB TITLE":"SENIOR PROGRAMMER\/ANALYST","DEPARTMENT":"FAMILY & SUPPORT","EMPLOYEE ANNUAL SALARY":"$91260.00","ESTIMATED ANNUAL SALARY MINUS FURLOUGHS":"$91260.00"},{"NAME":"ABRAHAM, DALINA D","JOB TITLE":"COORD OF COMMUNITY SERVICES","DEPARTMENT":"FAMILY & SUPPORT","EMPLOYEE ANNUAL SALARY":"$69684.00","ESTIMATED ANNUAL SALARY MINUS FURLOUGHS":"$63276.00"},{"NAME":"ABRAHAM, GIRLEY T","JOB TITLE":"CIVIL ENGINEER IV","DEPARTMENT":"WATER MGMNT","EMPLOYEE ANNUAL SALARY":"$96276.00","ESTIMATED ANNUAL SALARY MINUS FURLOUGHS":"$96276.00"},{"NAME":"ABRAHAM, GODWIN K","JOB TITLE":"ENGINEERING TECHNICIAN V","DEPARTMENT":"BUSINESS AFFAIRS","EMPLOYEE ANNUAL SALARY":"$84888.00","ESTIMATED ANNUAL SALARY MINUS FURLOUGHS":"$84888.00"},{"NAME":"ABRAHAM, T M","JOB TITLE":"PROGRAM DIR","DEPARTMENT":"COMMUNITY DEVELOPMENT","EMPLOYEE ANNUAL SALARY":"$102060.00","ESTIMATED ANNUAL SALARY MINUS FURLOUGHS":"$92675.00"},{"NAME":"ABRAMAVICIUS, ANNA A","JOB TITLE":"SUPERVISING TRAFFIC CONTROL AIDE","DEPARTMENT":"OEMC","EMPLOYEE ANNUAL SALARY":"$51216.00","ESTIMATED ANNUAL SALARY MINUS FURLOUGHS":"$49057.00"},{"NAME":"ABRAMS, DANIELLE T","JOB TITLE":"SANITATION LABORER","DEPARTMENT":"STREETS & SAN","EMPLOYEE ANNUAL SALARY":"$65894.00","ESTIMATED ANNUAL SALARY MINUS FURLOUGHS":"$60088.00"},{"NAME":"ABRAMS, HENRY L","JOB TITLE":"POLICE OFFICER","DEPARTMENT":"POLICE","EMPLOYEE ANNUAL SALARY":"$82878.00","ESTIMATED ANNUAL SALARY MINUS FURLOUGHS":"$82878.00"},{"NAME":"ABRAMSKI, JOHN E","JOB TITLE":"AMBULANCE COMMANDER","DEPARTMENT":"FIRE","EMPLOYEE ANNUAL SALARY":"$114498.00","ESTIMATED ANNUAL SALARY MINUS FURLOUGHS":"$114498.00"},{"NAME":"ABRATANSKI, MARK A","JOB TITLE":"FIREFIGHTER-EMT","DEPARTMENT":"FIRE","EMPLOYEE ANNUAL SALARY":"$71082.00","ESTIMATED ANNUAL SALARY MINUS FURLOUGHS":"$71082.00"},{"NAME":"ABREU, DILAN","JOB TITLE":"SEWER BRICKLAYER","DEPARTMENT":"WATER MGMNT","EMPLOYEE ANNUAL SALARY":"$81182.00","ESTIMATED ANNUAL SALARY MINUS FURLOUGHS":"$74028.00"},{"NAME":"ABREU, EDWIN","JOB TITLE":"TREE TRIMMER","DEPARTMENT":"STREETS & SAN","EMPLOYEE ANNUAL SALARY":"$67808.00","ESTIMATED ANNUAL SALARY MINUS FURLOUGHS":"$61833.00"},{"NAME":"ABREU, PEDRO","JOB TITLE":"WATER RATE TAKER","DEPARTMENT":"WATER MGMNT","EMPLOYEE ANNUAL SALARY":"$64248.00","ESTIMATED ANNUAL SALARY MINUS FURLOUGHS":"$58586.00"},{"NAME":"ABREU, ROBERTO J","JOB TITLE":"TRAFFIC SIGNAL REPAIRMAN","DEPARTMENT":"TRANSPORTN","EMPLOYEE ANNUAL SALARY":"$84968.00","ESTIMATED ANNUAL SALARY MINUS FURLOUGHS":"$77480.00"},{"NAME":"ABREU, ROSITA","JOB TITLE":"PERSONAL COMPUTER OPERATOR II","DEPARTMENT":"HEALTH","EMPLOYEE ANNUAL SALARY":"$53340.00","ESTIMATED ANNUAL SALARY MINUS FURLOUGHS":"$53340.00"},{"NAME":"ABREU, VICTOR","JOB TITLE":"SENIOR COMPANION","DEPARTMENT":"FAMILY & SUPPORT","EMPLOYEE ANNUAL SALARY":"$2756.00","ESTIMATED ANNUAL SALARY MINUS FURLOUGHS":"$2756.00"},{"NAME":"ABREU, VICTOR","JOB TITLE":"FIREFIGHTER","DEPARTMENT":"FIRE","EMPLOYEE ANNUAL SALARY":"$79926.00","ESTIMATED ANNUAL SALARY MINUS FURLOUGHS":"$79926.00"},{"NAME":"ABRON, FLOYD","JOB TITLE":"POLICE OFFICER","DEPARTMENT":"POLICE","EMPLOYEE ANNUAL SALARY":"$77238.00","ESTIMATED ANNUAL SALARY MINUS FURLOUGHS":"$77238.00"},{"NAME":"ABSTON, KATHY A","JOB TITLE":"POLICE OFFICER","DEPARTMENT":"POLICE","EMPLOYEE ANNUAL SALARY":"$79926.00","ESTIMATED ANNUAL SALARY MINUS FURLOUGHS":"$79926.00"},{"NAME":"ABUBAKER, MOHAMMED G","JOB TITLE":"SENIOR ENVIRONMENTAL INSPECTOR","DEPARTMENT":"ENVIRONMENT","EMPLOYEE ANNUAL SALARY":"$60708.00","ESTIMATED ANNUAL SALARY MINUS FURLOUGHS":"$60708.00"},{"NAME":"ABUTALEB, AHMAD H","JOB TITLE":"CIVIL ENGINEER II","DEPARTMENT":"WATER MGMNT","EMPLOYEE ANNUAL SALARY":"$80808.00","ESTIMATED ANNUAL SALARY MINUS FURLOUGHS":"$80808.00"},{"NAME":"ABUZANAT, ABDALLA H","JOB TITLE":"POLICE OFFICER","DEPARTMENT":"POLICE","EMPLOYEE ANNUAL SALARY":"$81090.00","ESTIMATED ANNUAL SALARY MINUS FURLOUGHS":"$81090.00"},{"NAME":"ACCARDO, ANTHONY D","JOB TITLE":"CONSTRUCTION LABORER","DEPARTMENT":"WATER MGMNT","EMPLOYEE ANNUAL SALARY":"$73216.00","ESTIMATED ANNUAL SALARY MINUS FURLOUGHS":"$66764.00"},{"NAME":"ACCARDO, JENNIFER A","JOB TITLE":"POLICE OFFICER","DEPARTMENT":"POLICE","EMPLOYEE ANNUAL SALARY":"$74628.00","ESTIMATED ANNUAL SALARY MINUS FURLOUGHS":"$74628.00"},{"NAME":"ACCARDO, ROSEMARY","JOB TITLE":"POLICE OFFICER","DEPARTMENT":"POLICE","EMPLOYEE ANNUAL SALARY":"$82878.00","ESTIMATED ANNUAL SALARY MINUS FURLOUGHS":"$82878.00"},{"NAME":"ACCARDO, THOMAS J","JOB TITLE":"POLICE OFFICER","DEPARTMENT":"POLICE","EMPLOYEE ANNUAL SALARY":"$77238.00","ESTIMATED ANNUAL SALARY MINUS FURLOUGHS":"$77238.00"},{"NAME":"ACCIARI, MICHAEL G","JOB TITLE":"COORD OF SPECIAL PROJECTS","DEPARTMENT":"STREETS & SAN","EMPLOYEE ANNUAL SALARY":"$97416.00","ESTIMATED ANNUAL SALARY MINUS FURLOUGHS":"$88458.00"},{"NAME":"ACCIARI, NICHOLAS B","JOB TITLE":"MOTOR TRUCK DRIVER","DEPARTMENT":"STREETS & SAN","EMPLOYEE ANNUAL SALARY":"$71469.00","ESTIMATED ANNUAL SALARY MINUS FURLOUGHS":"$71469.00"},{"NAME":"ACEVEDO JR, JOE D","JOB TITLE":"WATCHMAN","DEPARTMENT":"WATER MGMNT","EMPLOYEE ANNUAL SALARY":"$40019.00","ESTIMATED ANNUAL SALARY MINUS FURLOUGHS":"$36493.00"},{"NAME":"ACEVEDO, AARON F","JOB TITLE":"POLICE OFFICER","DEPARTMENT":"POLICE","EMPLOYEE ANNUAL SALARY":"$60918.00","ESTIMATED ANNUAL SALARY MINUS FURLOUGHS":"$60918.00"},{"NAME":"ACEVEDO, ALEJANDRO R","JOB TITLE":"POLICE OFFICER","DEPARTMENT":"POLICE","EMPLOYEE ANNUAL SALARY":"$74628.00","ESTIMATED ANNUAL SALARY MINUS FURLOUGHS":"$74628.00"},{"NAME":"ACEVEDO, BIENVENIDO","JOB TITLE":"POLICE OFFICER","DEPARTMENT":"POLICE","EMPLOYEE ANNUAL SALARY":"$77238.00","ESTIMATED ANNUAL SALARY MINUS FURLOUGHS":"$77238.00"},{"NAME":"ACEVEDO, CLARISSA","JOB TITLE":"POLICE OFFICER","DEPARTMENT":"POLICE","EMPLOYEE ANNUAL SALARY":"$82878.00","ESTIMATED ANNUAL SALARY MINUS FURLOUGHS":"$82878.00"},{"NAME":"ACEVEDO, DAILHA","JOB TITLE":"COMMUNICABLE DISEASE CONTROL INVESTIGATOR II","DEPARTMENT":"HEALTH","EMPLOYEE ANNUAL SALARY":"$48108.00","ESTIMATED ANNUAL SALARY MINUS FURLOUGHS":"$48108.00"},{"NAME":"ACEVEDO, EDWARD","JOB TITLE":"POLICE OFFICER","DEPARTMENT":"POLICE","EMPLOYEE ANNUAL SALARY":"$74628.00","ESTIMATED ANNUAL SALARY MINUS FURLOUGHS":"$74628.00"},{"NAME":"ACEVEDO, EDWIN C","JOB TITLE":"FIREFIGHTER","DEPARTMENT":"FIRE","EMPLOYEE ANNUAL SALARY":"$83148.00","ESTIMATED ANNUAL SALARY MINUS FURLOUGHS":"$83148.00"},{"NAME":"ACEVEDO, GILBERT","JOB TITLE":"LIEUTENANT-EMT","DEPARTMENT":"FIRE","EMPLOYEE ANNUAL SALARY":"$103704.00","ESTIMATED ANNUAL SALARY MINUS FURLOUGHS":"$103704.00"},{"NAME":"ACEVEDO, JASON M","JOB TITLE":"POLICE OFFICER","DEPARTMENT":"POLICE","EMPLOYEE ANNUAL SALARY":"$74628.00","ESTIMATED ANNUAL SALARY MINUS FURLOUGHS":"$74628.00"},{"NAME":"ACEVEDO, JAVIER","JOB TITLE":"ASPHALT HELPER","DEPARTMENT":"TRANSPORTN","EMPLOYEE ANNUAL SALARY":"$73216.00","ESTIMATED ANNUAL SALARY MINUS FURLOUGHS":"$66764.00"},{"NAME":"ACEVEDO, JEFF","JOB TITLE":"POLICE OFFICER","DEPARTMENT":"POLICE","EMPLOYEE ANNUAL SALARY":"$79926.00","ESTIMATED ANNUAL SALARY MINUS FURLOUGHS":"$79926.00"},{"NAME":"ACEVEDO, JOSE A","JOB TITLE":"MOTOR TRUCK DRIVER","DEPARTMENT":"WATER MGMNT","EMPLOYEE ANNUAL SALARY":"$70408.00","ESTIMATED ANNUAL SALARY MINUS FURLOUGHS":"$70408.00"},{"NAME":"ACEVEDO, LOUIS N","JOB TITLE":"MOTOR TRUCK DRIVER","DEPARTMENT":"GENERAL SERVICES","EMPLOYEE ANNUAL SALARY":"$70408.00","ESTIMATED ANNUAL SALARY MINUS FURLOUGHS":"$70408.00"},{"NAME":"ACEVEDO, MANUEL A","JOB TITLE":"FIREFIGHTER","DEPARTMENT":"FIRE","EMPLOYEE ANNUAL SALARY":"$77238.00","ESTIMATED ANNUAL SALARY MINUS FURLOUGHS":"$77238.00"},{"NAME":"ACEVEDO, MARCO A","JOB TITLE":"POLICE OFFICER","DEPARTMENT":"POLICE","EMPLOYEE ANNUAL SALARY":"$86508.00","ESTIMATED ANNUAL SALARY MINUS FURLOUGHS":"$86508.00"},{"NAME":"ACEVEDO, MARISOL","JOB TITLE":"SENIOR PUBLIC INFORMATION OFFICER","DEPARTMENT":"BUSINESS AFFAIRS","EMPLOYEE ANNUAL SALARY":"$80916.00","ESTIMATED ANNUAL SALARY MINUS FURLOUGHS":"$73475.00"},{"NAME":"ACEVEDO, MARTIN J","JOB TITLE":"POLICE OFFICER","DEPARTMENT":"POLICE","EMPLOYEE ANNUAL SALARY":"$77238.00","ESTIMATED ANNUAL SALARY MINUS FURLOUGHS":"$77238.00"},{"NAME":"ACEVEDO, MIKE","JOB TITLE":"AVIATION SECURITY OFFICER","DEPARTMENT":"AVIATION","EMPLOYEE ANNUAL SALARY":"$53628.00","ESTIMATED ANNUAL SALARY MINUS FURLOUGHS":"$51368.00"},{"NAME":"ACEVEDO, NADINE M","JOB TITLE":"POLICE OFFICER","DEPARTMENT":"POLICE","EMPLOYEE ANNUAL SALARY":"$77238.00","ESTIMATED ANNUAL SALARY MINUS FURLOUGHS":"$77238.00"},{"NAME":"ACEVEDO, RAFAEL","JOB TITLE":"POLICE OFFICER","DEPARTMENT":"POLICE","EMPLOYEE ANNUAL SALARY":"$74628.00","ESTIMATED ANNUAL SALARY MINUS FURLOUGHS":"$74628.00"},{"NAME":"ACEVEDO, SUSAN","JOB TITLE":"CEMENT MIXER","DEPARTMENT":"TRANSPORTN","EMPLOYEE ANNUAL SALARY":"$73216.00","ESTIMATED ANNUAL SALARY MINUS FURLOUGHS":"$66764.00"},{"NAME":"ACEVEDO, VERONICA","JOB TITLE":"POLICE OFFICER","DEPARTMENT":"POLICE","EMPLOYEE ANNUAL SALARY":"$79926.00","ESTIMATED ANNUAL SALARY MINUS FURLOUGHS":"$79926.00"},{"NAME":"ACEVES, JUAN C","JOB TITLE":"POLICE OFFICER","DEPARTMENT":"POLICE","EMPLOYEE ANNUAL SALARY":"$74628.00","ESTIMATED ANNUAL SALARY MINUS FURLOUGHS":"$74628.00"},{"NAME":"ACEVEZ, ANTHONY E","JOB TITLE":"POLICE OFFICER","DEPARTMENT":"POLICE","EMPLOYEE ANNUAL SALARY":"$77238.00","ESTIMATED ANNUAL SALARY MINUS FURLOUGHS":"$77238.00"},{"NAME":"ACHILLES, AMBER L","JOB TITLE":"ASST CORPORATION COUNSEL","DEPARTMENT":"LAW","EMPLOYEE ANNUAL SALARY":"$87900.00","ESTIMATED ANNUAL SALARY MINUS FURLOUGHS":"$79817.00"},{"NAME":"ACHILLY, LISA S","JOB TITLE":"POLICE OFFICER","DEPARTMENT":"POLICE","EMPLOYEE ANNUAL SALARY":"$79926.00","ESTIMATED ANNUAL SALARY MINUS FURLOUGHS":"$79926.00"},{"NAME":"ACHTEL, SCOTT R","JOB TITLE":"FIREFIGHTER","DEPARTMENT":"FIRE","EMPLOYEE ANNUAL SALARY":"$77238.00","ESTIMATED ANNUAL SALARY MINUS FURLOUGHS":"$77238.00"},{"NAME":"ACKERMAN, JAMES V","JOB TITLE":"LABORER","DEPARTMENT":"TRANSPORTN","EMPLOYEE ANNUAL SALARY":"$73216.00","ESTIMATED ANNUAL SALARY MINUS FURLOUGHS":"$66764.00"},{"NAME":"ACKLIN, QIANA D","JOB TITLE":"CROSSING GUARD","DEPARTMENT":"POLICE","EMPLOYEE ANNUAL SALARY":"$15319.00","ESTIMATED ANNUAL SALARY MINUS FURLOUGHS":"$15319.00"},{"NAME":"ACOSTA, ARTHUR J","JOB TITLE":"SANITATION LABORER","DEPARTMENT":"STREETS & SAN","EMPLOYEE ANNUAL SALARY":"$65894.00","ESTIMATED ANNUAL SALARY MINUS FURLOUGHS":"$60088.00"},{"NAME":"ACOSTA, JESSE A","JOB TITLE":"POLICE OFFICER","DEPARTMENT":"POLICE","EMPLOYEE ANNUAL SALARY":"$79926.00","ESTIMATED ANNUAL SALARY MINUS FURLOUGHS":"$79926.00"},{"NAME":"ACOSTA, MARIO A","JOB TITLE":"POLICE OFFICER","DEPARTMENT":"POLICE","EMPLOYEE ANNUAL SALARY":"$77238.00","ESTIMATED ANNUAL SALARY MINUS FURLOUGHS":"$77238.00"},{"NAME":"ACOSTA, MARTHA A","JOB TITLE":"LIBRARY ASSOCIATE","DEPARTMENT":"PUBLIC LIBRARY","EMPLOYEE ANNUAL SALARY":"$57264.00","ESTIMATED ANNUAL SALARY MINUS FURLOUGHS":"$57264.00"},{"NAME":"ACOSTA, MICHELE D","JOB TITLE":"POLICE OFFICER","DEPARTMENT":"POLICE","EMPLOYEE ANNUAL SALARY":"$77238.00","ESTIMATED ANNUAL SALARY MINUS FURLOUGHS":"$77238.00"},{"NAME":"ACOSTA, PABLO S","JOB TITLE":"SANITATION LABORER","DEPARTMENT":"STREETS & SAN","EMPLOYEE ANNUAL SALARY":"$65894.00","ESTIMATED ANNUAL SALARY MINUS FURLOUGHS":"$60088.00"},{"NAME":"ACOSTA, ROSA M","JOB TITLE":"PARKING ENFORCEMENT AIDE","DEPARTMENT":"AVIATION","EMPLOYEE ANNUAL SALARY":"$51216.00","ESTIMATED ANNUAL SALARY MINUS FURLOUGHS":"$49057.00"},{"NAME":"ACOSTA, SEGUNDINO","JOB TITLE":"REFUSE COLLECTION COORD","DEPARTMENT":"STREETS & SAN","EMPLOYEE ANNUAL SALARY":"$73848.00","ESTIMATED ANNUAL SALARY MINUS FURLOUGHS":"$67340.00"},{"NAME":"ACRES, ANTHONY E","JOB TITLE":"CONSTRUCTION LABORER","DEPARTMENT":"GENERAL SERVICES","EMPLOYEE ANNUAL SALARY":"$73216.00","ESTIMATED ANNUAL SALARY MINUS FURLOUGHS":"$66764.00"},{"NAME":"ACRES, EUGENE","JOB TITLE":"CONSTRUCTION LABORER","DEPARTMENT":"WATER MGMNT","EMPLOYEE ANNUAL SALARY":"$73216.00","ESTIMATED ANNUAL SALARY MINUS FURLOUGHS":"$66764.00"},{"NAME":"ACSVECS, ZAIREH","JOB TITLE":"POLICE OFFICER","DEPARTMENT":"POLICE","EMPLOYEE ANNUAL SALARY":"$43104.00","ESTIMATED ANNUAL SALARY MINUS FURLOUGHS":"$43104.00"},{"NAME":"ADAIR, KENNETH R","JOB TITLE":"POLICE OFFICER","DEPARTMENT":"POLICE","EMPLOYEE ANNUAL SALARY":"$74628.00","ESTIMATED ANNUAL SALARY MINUS FURLOUGHS":"$74628.00"},{"NAME":"ADAIR, STEVEN","JOB TITLE":"SANITATION LABORER","DEPARTMENT":"STREETS & SAN","EMPLOYEE ANNUAL SALARY":"$65894.00","ESTIMATED ANNUAL SALARY MINUS FURLOUGHS":"$60088.00"},{"NAME":"ADAM, ELIZABETH","JOB TITLE":"STAFF ASSISTANT - EXCLUDED","DEPARTMENT":"ADMIN HEARNG","EMPLOYEE ANNUAL SALARY":"$67224.00","ESTIMATED ANNUAL SALARY MINUS FURLOUGHS":"$61042.00"},{"NAME":"ADAM, MICHAEL A","JOB TITLE":"MOTOR TRUCK DRIVER","DEPARTMENT":"TRANSPORTN","EMPLOYEE ANNUAL SALARY":"$70408.00","ESTIMATED ANNUAL SALARY MINUS FURLOUGHS":"$70408.00"},{"NAME":"ADAM, RICHARD","JOB TITLE":"FOREMAN OF MOTOR TRUCK DRIVERS","DEPARTMENT":"STREETS & SAN","EMPLOYEE ANNUAL SALARY":"$74277.00","ESTIMATED ANNUAL SALARY MINUS FURLOUGHS":"$74277.00"},{"NAME":"ADAMCZYK JR, JAN","JOB TITLE":"BOOTER - PARKING","DEPARTMENT":"REVENUE","EMPLOYEE ANNUAL SALARY":"$63440.00","ESTIMATED ANNUAL SALARY MINUS FURLOUGHS":"$63440.00"},{"NAME":"ADAMCZYK, LAWRENCE M","JOB TITLE":"FIREFIGHTER","DEPARTMENT":"FIRE","EMPLOYEE ANNUAL SALARY":"$79926.00","ESTIMATED ANNUAL SALARY MINUS FURLOUGHS":"$79926.00"},{"NAME":"ADAME, PEDRO","JOB TITLE":"CUSTODIAL WORKER","DEPARTMENT":"AVIATION","EMPLOYEE ANNUAL SALARY":"$38584.00","ESTIMATED ANNUAL SALARY MINUS FURLOUGHS":"$35184.00"},{"NAME":"ADAMIAK, SIMON P","JOB TITLE":"POLICE OFFICER","DEPARTMENT":"POLICE","EMPLOYEE ANNUAL SALARY":"$74628.00","ESTIMATED ANNUAL SALARY MINUS FURLOUGHS":"$74628.00"},{"NAME":"ADAMIK, JEFFREY S","JOB TITLE":"POLICE OFFICER","DEPARTMENT":"POLICE","EMPLOYEE ANNUAL SALARY":"$86508.00","ESTIMATED ANNUAL SALARY MINUS FURLOUGHS":"$86508.00"},{"NAME":"ADAMIK, MATTHEW W","JOB TITLE":"PARAMEDIC","DEPARTMENT":"FIRE","EMPLOYEE ANNUAL SALARY":"$64374.00","ESTIMATED ANNUAL SALARY MINUS FURLOUGHS":"$64374.00"},{"NAME":"ADAMOVITZ, RANETTA","JOB TITLE":"POLICE OFFICER","DEPARTMENT":"POLICE","EMPLOYEE ANNUAL SALARY":"$82878.00","ESTIMATED ANNUAL SALARY MINUS FURLOUGHS":"$82878.00"},{"NAME":"ADAMOW, JEFFREY W","JOB TITLE":"FIREFIGHTER\/PARAMEDIC","DEPARTMENT":"FIRE","EMPLOYEE ANNUAL SALARY":"$69210.00","ESTIMATED ANNUAL SALARY MINUS FURLOUGHS":"$69210.00"},{"NAME":"ADAMOWSKI, ANDREW J","JOB TITLE":"POOL MOTOR TRUCK DRIVER","DEPARTMENT":"AVIATION","EMPLOYEE ANNUAL SALARY":"$70408.00","ESTIMATED ANNUAL SALARY MINUS FURLOUGHS":"$70408.00"},{"NAME":"ADAMS EL, WARREN","JOB TITLE":"CROSSING GUARD","DEPARTMENT":"POLICE","EMPLOYEE ANNUAL SALARY":"$16806.00","ESTIMATED ANNUAL SALARY MINUS FURLOUGHS":"$16806.00"},{"NAME":"ADAMS JR, EDWARD J","JOB TITLE":"SERGEANT","DEPARTMENT":"POLICE","EMPLOYEE ANNUAL SALARY":"$98766.00","ESTIMATED ANNUAL SALARY MINUS FURLOUGHS":"$98766.00"},{"NAME":"ADAMS JR, JERRY M","JOB TITLE":"POLICE OFFICER","DEPARTMENT":"POLICE","EMPLOYEE ANNUAL SALARY":"$79926.00","ESTIMATED ANNUAL SALARY MINUS FURLOUGHS":"$79926.00"},{"NAME":"ADAMS JR, JESSE D","JOB TITLE":"LABORER (BUREAU OF ELECTRICITY)","DEPARTMENT":"REVENUE","EMPLOYEE ANNUAL SALARY":"$73216.00","ESTIMATED ANNUAL SALARY MINUS FURLOUGHS":"$66764.00"},{"NAME":"ADAMS JR, JOHN W","JOB TITLE":"FIREFIGHTER-EMT","DEPARTMENT":"FIRE","EMPLOYEE ANNUAL SALARY":"$67596.00","ESTIMATED ANNUAL SALARY MINUS FURLOUGHS":"$67596.00"},{"NAME":"ADAMS THOMAS, CHEEAREASE R","JOB TITLE":"PUBLIC HEALTH ADMINISTRATOR I","DEPARTMENT":"HEALTH","EMPLOYEE ANNUAL SALARY":"$61308.00","ESTIMATED ANNUAL SALARY MINUS FURLOUGHS":"$61308.00"},{"NAME":"ADAMS, ALPHA A","JOB TITLE":"SOCIAL WORK ASST","DEPARTMENT":"HEALTH","EMPLOYEE ANNUAL SALARY":"$67296.00","ESTIMATED ANNUAL SALARY MINUS FURLOUGHS":"$67296.00"},{"NAME":"ADAMS, ANITA R","JOB TITLE":"SANITATION LABORER","DEPARTMENT":"STREETS & SAN","EMPLOYEE ANNUAL SALARY":"$65894.00","ESTIMATED ANNUAL SALARY MINUS FURLOUGHS":"$60088.00"},{"NAME":"ADAMS, BILLIE W","JOB TITLE":"SUPERVISING PHYSICIAN","DEPARTMENT":"HEALTH","EMPLOYEE ANNUAL SALARY":"$71989.00","ESTIMATED ANNUAL SALARY MINUS FURLOUGHS":"$65369.00"},{"NAME":"ADAMS, CRAIG W","JOB TITLE":"POLICE OFFICER","DEPARTMENT":"POLICE","EMPLOYEE ANNUAL SALARY":"$82878.00","ESTIMATED ANNUAL SALARY MINUS FURLOUGHS":"$82878.00"},{"NAME":"ADAMS, DAVID","JOB TITLE":"POLICE OFFICER","DEPARTMENT":"POLICE","EMPLOYEE ANNUAL SALARY":"$77238.00","ESTIMATED ANNUAL SALARY MINUS FURLOUGHS":"$77238.00"},{"NAME":"ADAMS, DAVID E","JOB TITLE":"SPECIAL EVENTS COORD III","DEPARTMENT":"CULTURAL AFFAIRS","EMPLOYEE ANNUAL SALARY":"$73752.00","ESTIMATED ANNUAL SALARY MINUS FURLOUGHS":"$66970.00"},{"NAME":"ADAMS, DENIS H","JOB TITLE":"CLINICAL THERAPIST III","DEPARTMENT":"POLICE","EMPLOYEE ANNUAL SALARY":"$88140.00","ESTIMATED ANNUAL SALARY MINUS FURLOUGHS":"$88140.00"},{"NAME":"ADAMS, DWAYNE D","JOB TITLE":"POLICE OFFICER","DEPARTMENT":"POLICE","EMPLOYEE ANNUAL SALARY":"$74628.00","ESTIMATED ANNUAL SALARY MINUS FURLOUGHS":"$74628.00"},{"NAME":"ADAMS, ERWIN","JOB TITLE":"ASPHALT HELPER","DEPARTMENT":"TRANSPORTN","EMPLOYEE ANNUAL SALARY":"$73216.00","ESTIMATED ANNUAL SALARY MINUS FURLOUGHS":"$66764.00"},{"NAME":"ADAMS, EULA M","JOB TITLE":"DATA ENTRY OPERATOR","DEPARTMENT":"WATER MGMNT","EMPLOYEE ANNUAL SALARY":"$42264.00","ESTIMATED ANNUAL SALARY MINUS FURLOUGHS":"$42264.00"},{"NAME":"ADAMS, GARY W","JOB TITLE":"SANITATION LABORER","DEPARTMENT":"STREETS & SAN","EMPLOYEE ANNUAL SALARY":"$65894.00","ESTIMATED ANNUAL SALARY MINUS FURLOUGHS":"$60088.00"},{"NAME":"ADAMS, GREGORY M","JOB TITLE":"AVIATION SECURITY OFFICER","DEPARTMENT":"AVIATION","EMPLOYEE ANNUAL SALARY":"$58860.00","ESTIMATED ANNUAL SALARY MINUS FURLOUGHS":"$56379.00"},{"NAME":"ADAMS, GREGORY W","JOB TITLE":"ADMINISTRATIVE ASST III","DEPARTMENT":"BUSINESS AFFAIRS","EMPLOYEE ANNUAL SALARY":"$61308.00","ESTIMATED ANNUAL SALARY MINUS FURLOUGHS":"$61308.00"},{"NAME":"ADAMS, HAROLD","JOB TITLE":"CEMENT MIXER","DEPARTMENT":"TRANSPORTN","EMPLOYEE ANNUAL SALARY":"$73216.00","ESTIMATED ANNUAL SALARY MINUS FURLOUGHS":"$66764.00"},{"NAME":"ADAMS, HELEN S","JOB TITLE":"POLICE OFFICER","DEPARTMENT":"POLICE","EMPLOYEE ANNUAL SALARY":"$82878.00","ESTIMATED ANNUAL SALARY MINUS FURLOUGHS":"$82878.00"},{"NAME":"ADAMS, JAMES W","JOB TITLE":"POLICE OFFICER","DEPARTMENT":"POLICE","EMPLOYEE ANNUAL SALARY":"$86508.00","ESTIMATED ANNUAL SALARY MINUS FURLOUGHS":"$86508.00"},{"NAME":"ADAMS, JOHN W","JOB TITLE":"POLICE OFFICER","DEPARTMENT":"POLICE","EMPLOYEE ANNUAL SALARY":"$79926.00","ESTIMATED ANNUAL SALARY MINUS FURLOUGHS":"$79926.00"},{"NAME":"ADAMS, LEAH","JOB TITLE":"ACCOUNTING TECHNICIAN II","DEPARTMENT":"COMMUNITY DEVELOPMENT","EMPLOYEE ANNUAL SALARY":"$53340.00","ESTIMATED ANNUAL SALARY MINUS FURLOUGHS":"$53340.00"},{"NAME":"ADAMS, MARJORIE","JOB TITLE":"HUMAN SERVICE WORKER","DEPARTMENT":"FAMILY & SUPPORT","EMPLOYEE ANNUAL SALARY":"$67296.00","ESTIMATED ANNUAL SALARY MINUS FURLOUGHS":"$67296.00"},{"NAME":"ADAMS, MARJORIE E","JOB TITLE":"LIBRARY PAGE","DEPARTMENT":"PUBLIC LIBRARY","EMPLOYEE ANNUAL SALARY":"$11471.00","ESTIMATED ANNUAL SALARY MINUS FURLOUGHS":"$11471.00"},{"NAME":"ADAMS, MAURICE D","JOB TITLE":"ELECTRICAL MECHANIC","DEPARTMENT":"GENERAL SERVICES","EMPLOYEE ANNUAL SALARY":"$84032.00","ESTIMATED ANNUAL SALARY MINUS FURLOUGHS":"$76627.00"},{"NAME":"ADAMS, MAURICE R","JOB TITLE":"PROPERTY CUSTODIAN","DEPARTMENT":"POLICE","EMPLOYEE ANNUAL SALARY":"$55872.00","ESTIMATED ANNUAL SALARY MINUS FURLOUGHS":"$55872.00"},{"NAME":"ADAMS, MICHAEL A","JOB TITLE":"POLICE OFFICER","DEPARTMENT":"POLICE","EMPLOYEE ANNUAL SALARY":"$86508.00","ESTIMATED ANNUAL SALARY MINUS FURLOUGHS":"$86508.00"},{"NAME":"ADAMS, MICHAEL J","JOB TITLE":"WATCHMAN","DEPARTMENT":"GENERAL SERVICES","EMPLOYEE ANNUAL SALARY":"$40019.00","ESTIMATED ANNUAL SALARY MINUS FURLOUGHS":"$36493.00"},{"NAME":"ADAMS, OLIVIA I","JOB TITLE":"LEGAL SECRETARY","DEPARTMENT":"LAW","EMPLOYEE ANNUAL SALARY":"$67296.00","ESTIMATED ANNUAL SALARY MINUS FURLOUGHS":"$67296.00"},{"NAME":"ADAMS, QUAN R","JOB TITLE":"POOL MOTOR TRUCK DRIVER","DEPARTMENT":"STREETS & SAN","EMPLOYEE ANNUAL SALARY":"$17602.00","ESTIMATED ANNUAL SALARY MINUS FURLOUGHS":"$17602.00"},{"NAME":"ADAMS, RAPHERES","JOB TITLE":"WATCHMAN","DEPARTMENT":"WATER MGMNT","EMPLOYEE ANNUAL SALARY":"$40019.00","ESTIMATED ANNUAL SALARY MINUS FURLOUGHS":"$36493.00"},{"NAME":"ADAMS, RAYMOND T","JOB TITLE":"LIEUTENANT","DEPARTMENT":"FIRE","EMPLOYEE ANNUAL SALARY":"$92778.00","ESTIMATED ANNUAL SALARY MINUS FURLOUGHS":"$92778.00"},{"NAME":"ADAMS, REGINALD K","JOB TITLE":"PLUMBING INSPECTOR","DEPARTMENT":"BUILDINGS","EMPLOYEE ANNUAL SALARY":"$93840.00","ESTIMATED ANNUAL SALARY MINUS FURLOUGHS":"$85571.00"},{"NAME":"ADAMS, ROBERT L","JOB TITLE":"VENTILATION AND FURNACE INSPECTOR","DEPARTMENT":"BUILDINGS","EMPLOYEE ANNUAL SALARY":"$91104.00","ESTIMATED ANNUAL SALARY MINUS FURLOUGHS":"$83076.00"},{"NAME":"ADAMS, RYAN","JOB TITLE":"POLICE OFFICER","DEPARTMENT":"POLICE","EMPLOYEE ANNUAL SALARY":"$43104.00","ESTIMATED ANNUAL SALARY MINUS FURLOUGHS":"$43104.00"},{"NAME":"ADAMS, SHERYLL A","JOB TITLE":"LIBRARIAN II","DEPARTMENT":"PUBLIC LIBRARY","EMPLOYEE ANNUAL SALARY":"$73932.00","ESTIMATED ANNUAL SALARY MINUS FURLOUGHS":"$73932.00"},{"NAME":"ADAMS, STANLEY","JOB TITLE":"SUPVSR OF COMPENSATION","DEPARTMENT":"BUSINESS AFFAIRS","EMPLOYEE ANNUAL SALARY":"$80916.00","ESTIMATED ANNUAL SALARY MINUS FURLOUGHS":"$73475.00"},{"NAME":"ADAMS, TIMOTHY J","JOB TITLE":"POLICE OFFICER","DEPARTMENT":"POLICE","EMPLOYEE ANNUAL SALARY":"$77238.00","ESTIMATED ANNUAL SALARY MINUS FURLOUGHS":"$77238.00"},{"NAME":"ADAMS, VICKY M","JOB TITLE":"POLICE OFFICER","DEPARTMENT":"POLICE","EMPLOYEE ANNUAL SALARY":"$77238.00","ESTIMATED ANNUAL SALARY MINUS FURLOUGHS":"$77238.00"},{"NAME":"ADAMS, WILLIAM W","JOB TITLE":"LIEUTENANT-EMT","DEPARTMENT":"FIRE","EMPLOYEE ANNUAL SALARY":"$107064.00","ESTIMATED ANNUAL SALARY MINUS FURLOUGHS":"$107064.00"},{"NAME":"ADAMSKI, JERRY J","JOB TITLE":"POLICE OFFICER","DEPARTMENT":"POLICE","EMPLOYEE ANNUAL SALARY":"$74628.00","ESTIMATED ANNUAL SALARY MINUS FURLOUGHS":"$74628.00"},{"NAME":"ADAPON, NENITA P","JOB TITLE":"ACCOUNTING TECHNICIAN I","DEPARTMENT":"WATER MGMNT","EMPLOYEE ANNUAL SALARY":"$48576.00","ESTIMATED ANNUAL SALARY MINUS FURLOUGHS":"$48576.00"},{"NAME":"ADCOCK, DAVID G","JOB TITLE":"POLICE OFFICER","DEPARTMENT":"POLICE","EMPLOYEE ANNUAL SALARY":"$74628.00","ESTIMATED ANNUAL SALARY MINUS FURLOUGHS":"$74628.00"},{"NAME":"ADCOCK, MARK","JOB TITLE":"FOREMAN OF WINDOW WASHERS","DEPARTMENT":"AVIATION","EMPLOYEE ANNUAL SALARY":"$44580.00","ESTIMATED ANNUAL SALARY MINUS FURLOUGHS":"$40651.00"},{"NAME":"ADCOCK, TOMMY W","JOB TITLE":"CEMENT MIXER","DEPARTMENT":"TRANSPORTN","EMPLOYEE ANNUAL SALARY":"$73216.00","ESTIMATED ANNUAL SALARY MINUS FURLOUGHS":"$66764.00"},{"NAME":"ADDESSO JR, FRANK J","JOB TITLE":"MOTOR TRUCK DRIVER","DEPARTMENT":"WATER MGMNT","EMPLOYEE ANNUAL SALARY":"$70408.00","ESTIMATED ANNUAL SALARY MINUS FURLOUGHS":"$70408.00"},{"NAME":"ADDISON, LATASHA D","JOB TITLE":"LIBRARY PAGE","DEPARTMENT":"PUBLIC LIBRARY","EMPLOYEE ANNUAL SALARY":"$11471.00","ESTIMATED ANNUAL SALARY MINUS FURLOUGHS":"$11471.00"},{"NAME":"ADDISON, LEWIS","JOB TITLE":"LIBRARY ASSOCIATE","DEPARTMENT":"PUBLIC LIBRARY","EMPLOYEE ANNUAL SALARY":"$57264.00","ESTIMATED ANNUAL SALARY MINUS FURLOUGHS":"$57264.00"},{"NAME":"ADDUCI, MARK A","JOB TITLE":"LIEUTENANT","DEPARTMENT":"POLICE","EMPLOYEE ANNUAL SALARY":"$107820.00","ESTIMATED ANNUAL SALARY MINUS FURLOUGHS":"$107820.00"},{"NAME":"ADE, JAMES P","JOB TITLE":"POLICE OFFICER","DEPARTMENT":"POLICE","EMPLOYEE ANNUAL SALARY":"$43104.00","ESTIMATED ANNUAL SALARY MINUS FURLOUGHS":"$43104.00"},{"NAME":"ADE, JAMES P","JOB TITLE":"SERGEANT","DEPARTMENT":"POLICE","EMPLOYEE ANNUAL SALARY":"$98766.00","ESTIMATED ANNUAL SALARY MINUS FURLOUGHS":"$98766.00"},{"NAME":"ADEBAYO, BENJAMIN B","JOB TITLE":"BUILDING\/CONSTRUCTION INSPECTOR","DEPARTMENT":"BUILDINGS","EMPLOYEE ANNUAL SALARY":"$93120.00","ESTIMATED ANNUAL SALARY MINUS FURLOUGHS":"$84914.00"},{"NAME":"ADEBOYEJO, JOYCE A","JOB TITLE":"FINANCIAL OFFICER","DEPARTMENT":"FINANCE","EMPLOYEE ANNUAL SALARY":"$102060.00","ESTIMATED ANNUAL SALARY MINUS FURLOUGHS":"$92675.00"},{"NAME":"ADEGBORE, JUANITA","JOB TITLE":"POLICE OFFICER","DEPARTMENT":"POLICE","EMPLOYEE ANNUAL SALARY":"$77238.00","ESTIMATED ANNUAL SALARY MINUS FURLOUGHS":"$77238.00"},{"NAME":"ADEKA, IBILOLA I","JOB TITLE":"SUPERVISING DISEASE CONTROL INVESTIGATOR - EXCL","DEPARTMENT":"HEALTH","EMPLOYEE ANNUAL SALARY":"$67224.00","ESTIMATED ANNUAL SALARY MINUS FURLOUGHS":"$61042.00"},{"NAME":"ADEKALE, DAVID O","JOB TITLE":"TRAFFIC CONTROL AIDE-HOURLY","DEPARTMENT":"OEMC","EMPLOYEE ANNUAL SALARY":"$18886.00","ESTIMATED ANNUAL SALARY MINUS FURLOUGHS":"$18886.00"},{"NAME":"ADEKUNLE, MICHELLE","JOB TITLE":"STUDENT INTERN","DEPARTMENT":"TRANSPORTN","EMPLOYEE ANNUAL SALARY":"$21840.00","ESTIMATED ANNUAL SALARY MINUS FURLOUGHS":"$21840.00"},{"NAME":"ADELAKUN, NIKTE E","JOB TITLE":"POLICE OFFICER","DEPARTMENT":"POLICE","EMPLOYEE ANNUAL SALARY":"$74628.00","ESTIMATED ANNUAL SALARY MINUS FURLOUGHS":"$74628.00"},{"NAME":"ADELIZZI, JOY A","JOB TITLE":"DEPUTY COMMISSIONER","DEPARTMENT":"BUSINESS AFFAIRS","EMPLOYEE ANNUAL SALARY":"$116688.00","ESTIMATED ANNUAL SALARY MINUS FURLOUGHS":"$105958.00"},{"NAME":"ADELMAN, BRUCE E","JOB TITLE":"LEGISLATIVE AIDE","DEPARTMENT":"CITY COUNCIL","EMPLOYEE ANNUAL SALARY":"$19000.00","ESTIMATED ANNUAL SALARY MINUS FURLOUGHS":"$18126.00"},{"NAME":"ADEMOSU, ABIM","JOB TITLE":"TRAFFIC CONTROL AIDE-HOURLY","DEPARTMENT":"OEMC","EMPLOYEE ANNUAL SALARY":"$18886.00","ESTIMATED ANNUAL SALARY MINUS FURLOUGHS":"$18886.00"},{"NAME":"ADENI, MOHAMED K","JOB TITLE":"ACCOUNTANT IV","DEPARTMENT":"REVENUE","EMPLOYEE ANNUAL SALARY":"$83604.00","ESTIMATED ANNUAL SALARY MINUS FURLOUGHS":"$83604.00"},{"NAME":"ADESANYA, EMMANUEL S","JOB TITLE":"ENVIRONMENTAL ENGINEER II","DEPARTMENT":"ENVIRONMENT","EMPLOYEE ANNUAL SALARY":"$88140.00","ESTIMATED ANNUAL SALARY MINUS FURLOUGHS":"$88140.00"},{"NAME":"ADEYEMO, HORATIO A","JOB TITLE":"CIVIL ENGINEER III","DEPARTMENT":"TRANSPORTN","EMPLOYEE ANNUAL SALARY":"$88140.00","ESTIMATED ANNUAL SALARY MINUS FURLOUGHS":"$88140.00"},{"NAME":"ADEYEMO, MOJIROLA M","JOB TITLE":"PUBLIC HEALTH ADMINISTRATOR I","DEPARTMENT":"HEALTH","EMPLOYEE ANNUAL SALARY":"$58548.00","ESTIMATED ANNUAL SALARY MINUS FURLOUGHS":"$58548.00"},{"NAME":"ADKINS, MARC D","JOB TITLE":"POLICE OFFICER","DEPARTMENT":"POLICE","EMPLOYEE ANNUAL SALARY":"$82878.00","ESTIMATED ANNUAL SALARY MINUS FURLOUGHS":"$82878.00"},{"NAME":"ADKINS, MARCIEA L","JOB TITLE":"POLICE COMMUNICATIONS OPERATOR II","DEPARTMENT":"OEMC","EMPLOYEE ANNUAL SALARY":"$70884.00","ESTIMATED ANNUAL SALARY MINUS FURLOUGHS":"$67897.00"},{"NAME":"ADKINS, WILLIAM J","JOB TITLE":"FIRE COMMUNICATIONS OPERATOR II","DEPARTMENT":"OEMC","EMPLOYEE ANNUAL SALARY":"$83772.00","ESTIMATED ANNUAL SALARY MINUS FURLOUGHS":"$76390.00"},{"NAME":"ADLER, TRACY L","JOB TITLE":"POLICE OFFICER","DEPARTMENT":"POLICE","EMPLOYEE ANNUAL SALARY":"$71040.00","ESTIMATED ANNUAL SALARY MINUS FURLOUGHS":"$71040.00"},{"NAME":"ADLESICK JR, JOSEPH D","JOB TITLE":"POLICE OFFICER","DEPARTMENT":"POLICE","EMPLOYEE ANNUAL SALARY":"$77238.00","ESTIMATED ANNUAL SALARY MINUS FURLOUGHS":"$77238.00"},{"NAME":"ADOLFIE JR, WALTER S","JOB TITLE":"POLICE OFFICER","DEPARTMENT":"POLICE","EMPLOYEE ANNUAL SALARY":"$79926.00","ESTIMATED ANNUAL SALARY MINUS FURLOUGHS":"$79926.00"},{"NAME":"ADOLFIE, ELIZABETH U","JOB TITLE":"ADMINISTRATIVE ASST III","DEPARTMENT":"BUSINESS AFFAIRS","EMPLOYEE ANNUAL SALARY":"$58548.00","ESTIMATED ANNUAL SALARY MINUS FURLOUGHS":"$58548.00"},{"NAME":"ADOLPH, JOHN W","JOB TITLE":"ASST CORPORATION COUNSEL SUPVSR","DEPARTMENT":"LAW","EMPLOYEE ANNUAL SALARY":"$93840.00","ESTIMATED ANNUAL SALARY MINUS FURLOUGHS":"$85211.00"},{"NAME":"ADREANI, JOHN A","JOB TITLE":"POLICE OFFICER","DEPARTMENT":"POLICE","EMPLOYEE ANNUAL SALARY":"$79926.00","ESTIMATED ANNUAL SALARY MINUS FURLOUGHS":"$79926.00"},{"NAME":"ADREANI, JOHN J","JOB TITLE":"FIREFIGHTER-EMT","DEPARTMENT":"FIRE","EMPLOYEE ANNUAL SALARY":"$81096.00","ESTIMATED ANNUAL SALARY MINUS FURLOUGHS":"$81096.00"},{"NAME":"ADRIAN, CHERI A","JOB TITLE":"SERGEANT","DEPARTMENT":"POLICE","EMPLOYEE ANNUAL SALARY":"$95694.00","ESTIMATED ANNUAL SALARY MINUS FURLOUGHS":"$95694.00"},{"NAME":"ADRIAN, JOHN P","JOB TITLE":"ASST CHIEF AIRPORT OPERATIONS SUPVSR","DEPARTMENT":"AVIATION","EMPLOYEE ANNUAL SALARY":"$107004.00","ESTIMATED ANNUAL SALARY MINUS FURLOUGHS":"$97575.00"},{"NAME":"ADROW, GREGORY L","JOB TITLE":"PAINTER","DEPARTMENT":"TRANSPORTN","EMPLOYEE ANNUAL SALARY":"$79040.00","ESTIMATED ANNUAL SALARY MINUS FURLOUGHS":"$72075.00"},{"NAME":"AFFANEH, MAHIR A","JOB TITLE":"POLICE OFFICER","DEPARTMENT":"POLICE","EMPLOYEE ANNUAL SALARY":"$77238.00","ESTIMATED ANNUAL SALARY MINUS FURLOUGHS":"$77238.00"},{"NAME":"AFROZ, NAYYAR","JOB TITLE":"PSYCHIATRIST","DEPARTMENT":"HEALTH","EMPLOYEE ANNUAL SALARY":"$159669.00","ESTIMATED ANNUAL SALARY MINUS FURLOUGHS":"$144986.00"},{"NAME":"AFUANG, CESAR V","JOB TITLE":"AUDITOR IV","DEPARTMENT":"REVENUE","EMPLOYEE ANNUAL SALARY":"$105240.00","ESTIMATED ANNUAL SALARY MINUS FURLOUGHS":"$105240.00"},{"NAME":"AFZAL, RANA","JOB TITLE":"INQUIRY AIDE III","DEPARTMENT":"STREETS & SAN","EMPLOYEE ANNUAL SALARY":"$46428.00","ESTIMATED ANNUAL SALARY MINUS FURLOUGHS":"$46428.00"},{"NAME":"AGAR, BULENT B","JOB TITLE":"ASST PROJECT DIR","DEPARTMENT":"TRANSPORTN","EMPLOYEE ANNUAL SALARY":"$79464.00","ESTIMATED ANNUAL SALARY MINUS FURLOUGHS":"$72157.00"},{"NAME":"AGEE, LATANJA","JOB TITLE":"AVIATION SECURITY OFFICER","DEPARTMENT":"AVIATION","EMPLOYEE ANNUAL SALARY":"$51216.00","ESTIMATED ANNUAL SALARY MINUS FURLOUGHS":"$49057.00"},{"NAME":"AGEE, LAWRENCE","JOB TITLE":"POLICE OFFICER","DEPARTMENT":"POLICE","EMPLOYEE ANNUAL SALARY":"$74628.00","ESTIMATED ANNUAL SALARY MINUS FURLOUGHS":"$74628.00"},{"NAME":"AGIC, MICHAEL P","JOB TITLE":"LIBRARY ASSOCIATE","DEPARTMENT":"PUBLIC LIBRARY","EMPLOYEE ANNUAL SALARY":"$54564.00","ESTIMATED ANNUAL SALARY MINUS FURLOUGHS":"$54564.00"},{"NAME":"AGIN, LAURA M","JOB TITLE":"POLICE OFFICER","DEPARTMENT":"POLICE","EMPLOYEE ANNUAL SALARY":"$82878.00","ESTIMATED ANNUAL SALARY MINUS FURLOUGHS":"$82878.00"},{"NAME":"AGOSTA, JOSEPH J","JOB TITLE":"POLICE OFFICER","DEPARTMENT":"POLICE","EMPLOYEE ANNUAL SALARY":"$89646.00","ESTIMATED ANNUAL SALARY MINUS FURLOUGHS":"$89646.00"},{"NAME":"AGOSTINELLI, MICHAEL A","JOB TITLE":"FIREFIGHTER (PER ARBITRATORS AWARD)-PARAMEDIC","DEPARTMENT":"FIRE","EMPLOYEE ANNUAL SALARY":"$93000.00","ESTIMATED ANNUAL SALARY MINUS FURLOUGHS":"$93000.00"},{"NAME":"AGOSTO, HECTOR I","JOB TITLE":"POLICE OFFICER","DEPARTMENT":"POLICE","EMPLOYEE ANNUAL SALARY":"$74628.00","ESTIMATED ANNUAL SALARY MINUS FURLOUGHS":"$74628.00"},{"NAME":"AGREDANO, MARIO","JOB TITLE":"BRIDGE OPERATOR","DEPARTMENT":"TRANSPORTN","EMPLOYEE ANNUAL SALARY":"$48108.00","ESTIMATED ANNUAL SALARY MINUS FURLOUGHS":"$43869.00"},{"NAME":"AGRESTO, JOSEPH F","JOB TITLE":"GARAGE ATTENDANT","DEPARTMENT":"FLEET MANAGEMNT","EMPLOYEE ANNUAL SALARY":"$42432.00","ESTIMATED ANNUAL SALARY MINUS FURLOUGHS":"$42432.00"},{"NAME":"AGRON, EDUARDO","JOB TITLE":"POLICE OFFICER","DEPARTMENT":"POLICE","EMPLOYEE ANNUAL SALARY":"$89646.00","ESTIMATED ANNUAL SALARY MINUS FURLOUGHS":"$89646.00"},{"NAME":"AGRON, EDWIN","JOB TITLE":"POLICE OFFICER","DEPARTMENT":"POLICE","EMPLOYEE ANNUAL SALARY":"$74628.00","ESTIMATED ANNUAL SALARY MINUS FURLOUGHS":"$74628.00"},{"NAME":"AGSALUD JR, JUANITO S","JOB TITLE":"SANITATION LABORER","DEPARTMENT":"STREETS & SAN","EMPLOYEE ANNUAL SALARY":"$65894.00","ESTIMATED ANNUAL SALARY MINUS FURLOUGHS":"$60088.00"},{"NAME":"AGSALUD, FERNAN S","JOB TITLE":"SANITATION LABORER","DEPARTMENT":"STREETS & SAN","EMPLOYEE ANNUAL SALARY":"$65894.00","ESTIMATED ANNUAL SALARY MINUS FURLOUGHS":"$60088.00"},{"NAME":"AGUAYO, LUIS A","JOB TITLE":"FIREFIGHTER-EMT","DEPARTMENT":"FIRE","EMPLOYEE ANNUAL SALARY":"$78354.00","ESTIMATED ANNUAL SALARY MINUS FURLOUGHS":"$78354.00"},{"NAME":"AGUIAR, WILLIAM M","JOB TITLE":"ASST CORPORATION COUNSEL","DEPARTMENT":"LAW","EMPLOYEE ANNUAL SALARY":"$102492.00","ESTIMATED ANNUAL SALARY MINUS FURLOUGHS":"$93067.00"},{"NAME":"AGUILA, CAROL J","JOB TITLE":"LEGISLATIVE AIDE","DEPARTMENT":"CITY COUNCIL","EMPLOYEE ANNUAL SALARY":"$8851.00","ESTIMATED ANNUAL SALARY MINUS FURLOUGHS":"$8444.00"},{"NAME":"AGUILAR, ALFREDO","JOB TITLE":"SANITATION LABORER","DEPARTMENT":"STREETS & SAN","EMPLOYEE ANNUAL SALARY":"$70054.00","ESTIMATED ANNUAL SALARY MINUS FURLOUGHS":"$63881.00"},{"NAME":"AGUILAR, EFRAIN","JOB TITLE":"SANITATION LABORER","DEPARTMENT":"STREETS & SAN","EMPLOYEE ANNUAL SALARY":"$65894.00","ESTIMATED ANNUAL SALARY MINUS FURLOUGHS":"$60088.00"},{"NAME":"AGUILAR, ELMA M","JOB TITLE":"ANIMAL CARE AIDE I","DEPARTMENT":"ANIMAL CONTRL","EMPLOYEE ANNUAL SALARY":"$53340.00","ESTIMATED ANNUAL SALARY MINUS FURLOUGHS":"$53340.00"},{"NAME":"AGUILAR, ESTHER","JOB TITLE":"COORD OF SPECIAL PROJECTS","DEPARTMENT":"HEALTH","EMPLOYEE ANNUAL SALARY":"$80916.00","ESTIMATED ANNUAL SALARY MINUS FURLOUGHS":"$73475.00"},{"NAME":"AGUILAR, IRENE","JOB TITLE":"SANITATION LABORER","DEPARTMENT":"STREETS & SAN","EMPLOYEE ANNUAL SALARY":"$65894.00","ESTIMATED ANNUAL SALARY MINUS FURLOUGHS":"$60088.00"},{"NAME":"AGUILAR, JOSE CRUZ A","JOB TITLE":"SANITATION LABORER","DEPARTMENT":"STREETS & SAN","EMPLOYEE ANNUAL SALARY":"$65894.00","ESTIMATED ANNUAL SALARY MINUS FURLOUGHS":"$60088.00"},{"NAME":"AGUILAR, JOSEPH L","JOB TITLE":"FIREFIGHTER","DEPARTMENT":"FIRE","EMPLOYEE ANNUAL SALARY":"$83148.00","ESTIMATED ANNUAL SALARY MINUS FURLOUGHS":"$83148.00"},{"NAME":"AGUILAR, JOSEPHINE","JOB TITLE":"FIREFIGHTER","DEPARTMENT":"FIRE","EMPLOYEE ANNUAL SALARY":"$79926.00","ESTIMATED ANNUAL SALARY MINUS FURLOUGHS":"$79926.00"},{"NAME":"AGUILAR, JUANITA","JOB TITLE":"POOL MOTOR TRUCK DRIVER","DEPARTMENT":"AVIATION","EMPLOYEE ANNUAL SALARY":"$70408.00","ESTIMATED ANNUAL SALARY MINUS FURLOUGHS":"$70408.00"},{"NAME":"AGUILAR, JUANITA M","JOB TITLE":"EDITORIAL ASST","DEPARTMENT":"CITY CLERK","EMPLOYEE ANNUAL SALARY":"$50952.00","ESTIMATED ANNUAL SALARY MINUS FURLOUGHS":"$50952.00"},{"NAME":"AGUILAR, KARINA D","JOB TITLE":"POLICE OFFICER","DEPARTMENT":"POLICE","EMPLOYEE ANNUAL SALARY":"$77238.00","ESTIMATED ANNUAL SALARY MINUS FURLOUGHS":"$77238.00"},{"NAME":"AGUILAR, LOUIS","JOB TITLE":"SENIOR CLERK-ELECTIONS","DEPARTMENT":"BOARD OF ELECTION","EMPLOYEE ANNUAL SALARY":"$44352.00","ESTIMATED ANNUAL SALARY MINUS FURLOUGHS":"$40274.00"},{"NAME":"AGUILAR, LUIS","JOB TITLE":"POLICE OFFICER","DEPARTMENT":"POLICE","EMPLOYEE ANNUAL SALARY":"$77238.00","ESTIMATED ANNUAL SALARY MINUS FURLOUGHS":"$77238.00"},{"NAME":"AGUILAR, RAY R","JOB TITLE":"POLICE OFFICER","DEPARTMENT":"POLICE","EMPLOYEE ANNUAL SALARY":"$71040.00","ESTIMATED ANNUAL SALARY MINUS FURLOUGHS":"$71040.00"},{"NAME":"AGUILAR, RICARDO L","JOB TITLE":"ANIMAL CONTROL OFFICER","DEPARTMENT":"ANIMAL CONTRL","EMPLOYEE ANNUAL SALARY":"$58860.00","ESTIMATED ANNUAL SALARY MINUS FURLOUGHS":"$56379.00"},{"NAME":"AGUILAR, RICHARD L","JOB TITLE":"POLICE OFFICER","DEPARTMENT":"POLICE","EMPLOYEE ANNUAL SALARY":"$89646.00","ESTIMATED ANNUAL SALARY MINUS FURLOUGHS":"$89646.00"},{"NAME":"AGUILAR, ROBERT","JOB TITLE":"MOTOR TRUCK DRIVER","DEPARTMENT":"STREETS & SAN","EMPLOYEE ANNUAL SALARY":"$70408.00","ESTIMATED ANNUAL SALARY MINUS FURLOUGHS":"$70408.00"},{"NAME":"AGUILAR, ROBERT","JOB TITLE":"MOTOR TRUCK DRIVER","DEPARTMENT":"STREETS & SAN","EMPLOYEE ANNUAL SALARY":"$70408.00","ESTIMATED ANNUAL SALARY MINUS FURLOUGHS":"$70408.00"},{"NAME":"AGUILAR, TINA M","JOB TITLE":"ASSISTANT COMPLIANCE OFFICER","DEPARTMENT":"COMPLIANCE","EMPLOYEE ANNUAL SALARY":"$53844.00","ESTIMATED ANNUAL SALARY MINUS FURLOUGHS":"$48893.00"},{"NAME":"AGUILERA, CONSUELO M","JOB TITLE":"SERGEANT","DEPARTMENT":"POLICE","EMPLOYEE ANNUAL SALARY":"$98766.00","ESTIMATED ANNUAL SALARY MINUS FURLOUGHS":"$98766.00"},{"NAME":"AGUILERA, DANIEL","JOB TITLE":"POLICE OFFICER","DEPARTMENT":"POLICE","EMPLOYEE ANNUAL SALARY":"$79926.00","ESTIMATED ANNUAL SALARY MINUS FURLOUGHS":"$79926.00"},{"NAME":"AGUILERA, EDWARD M","JOB TITLE":"POLICE OFFICER","DEPARTMENT":"POLICE","EMPLOYEE ANNUAL SALARY":"$82878.00","ESTIMATED ANNUAL SALARY MINUS FURLOUGHS":"$82878.00"},{"NAME":"AGUILERA, JESUS","JOB TITLE":"SANITATION LABORER","DEPARTMENT":"STREETS & SAN","EMPLOYEE ANNUAL SALARY":"$65894.00","ESTIMATED ANNUAL SALARY MINUS FURLOUGHS":"$60088.00"},{"NAME":"AGUILERA, JUAN A","JOB TITLE":"STREET LIGHT REPAIR WORKER","DEPARTMENT":"TRANSPORTN","EMPLOYEE ANNUAL SALARY":"$84968.00","ESTIMATED ANNUAL SALARY MINUS FURLOUGHS":"$77480.00"},{"NAME":"AGUILERA, LINDA M","JOB TITLE":"POLICE OFFICER","DEPARTMENT":"POLICE","EMPLOYEE ANNUAL SALARY":"$74628.00","ESTIMATED ANNUAL SALARY MINUS FURLOUGHS":"$74628.00"},{"NAME":"AGUILERA, TONY","JOB TITLE":"MOTOR TRUCK DRIVER","DEPARTMENT":"STREETS & SAN","EMPLOYEE ANNUAL SALARY":"$70408.00","ESTIMATED ANNUAL SALARY MINUS FURLOUGHS":"$70408.00"},{"NAME":"AGUILOS, CESAR M","JOB TITLE":"POLICE OFFICER","DEPARTMENT":"POLICE","EMPLOYEE ANNUAL SALARY":"$79926.00","ESTIMATED ANNUAL SALARY MINUS FURLOUGHS":"$79926.00"},{"NAME":"AGUINAGA, JAMES M","JOB TITLE":"FIRE ENGINEER","DEPARTMENT":"FIRE","EMPLOYEE ANNUAL SALARY":"$92268.00","ESTIMATED ANNUAL SALARY MINUS FURLOUGHS":"$92268.00"},{"NAME":"AGUINAGA, JOHN P","JOB TITLE":"POLICE OFFICER","DEPARTMENT":"POLICE","EMPLOYEE ANNUAL SALARY":"$85278.00","ESTIMATED ANNUAL SALARY MINUS FURLOUGHS":"$85278.00"},{"NAME":"AGUINAGA, JOSEPH C","JOB TITLE":"POLICE OFFICER","DEPARTMENT":"POLICE","EMPLOYEE ANNUAL SALARY":"$85278.00","ESTIMATED ANNUAL SALARY MINUS FURLOUGHS":"$85278.00"},{"NAME":"AGUINAGA, MEGAN E","JOB TITLE":"POLICE OFFICER","DEPARTMENT":"POLICE","EMPLOYEE ANNUAL SALARY":"$74628.00","ESTIMATED ANNUAL SALARY MINUS FURLOUGHS":"$74628.00"},{"NAME":"AGUINAGA, RICHARD J","JOB TITLE":"CAPTAIN","DEPARTMENT":"POLICE","EMPLOYEE ANNUAL SALARY":"$126336.00","ESTIMATED ANNUAL SALARY MINUS FURLOUGHS":"$126336.00"},{"NAME":"AGUIRRE, ANTHONY J","JOB TITLE":"POLICE OFFICER","DEPARTMENT":"POLICE","EMPLOYEE ANNUAL SALARY":"$77238.00","ESTIMATED ANNUAL SALARY MINUS FURLOUGHS":"$77238.00"},{"NAME":"AGUIRRE, ENRIQUE","JOB TITLE":"POLICE OFFICER","DEPARTMENT":"POLICE","EMPLOYEE ANNUAL SALARY":"$60918.00","ESTIMATED ANNUAL SALARY MINUS FURLOUGHS":"$60918.00"},{"NAME":"AGUIRRE, GUADALUPE","JOB TITLE":"ADMINISTRATIVE SERVICES OFFICER II","DEPARTMENT":"TRANSPORTN","EMPLOYEE ANNUAL SALARY":"$84780.00","ESTIMATED ANNUAL SALARY MINUS FURLOUGHS":"$76984.00"},{"NAME":"AGUIRRE, GUADALUPE G","JOB TITLE":"POLICE OFFICER","DEPARTMENT":"POLICE","EMPLOYEE ANNUAL SALARY":"$43104.00","ESTIMATED ANNUAL SALARY MINUS FURLOUGHS":"$43104.00"},{"NAME":"AGUIRRE, JESSE","JOB TITLE":"CUSTODIAL WORKER","DEPARTMENT":"GENERAL SERVICES","EMPLOYEE ANNUAL SALARY":"$38584.00","ESTIMATED ANNUAL SALARY MINUS FURLOUGHS":"$35184.00"},{"NAME":"AGUIRRE, JESSE M","JOB TITLE":"FIRE ENGINEER","DEPARTMENT":"FIRE","EMPLOYEE ANNUAL SALARY":"$89646.00","ESTIMATED ANNUAL SALARY MINUS FURLOUGHS":"$89646.00"},{"NAME":"AGUIRRE, JOSEPH R","JOB TITLE":"POLICE OFFICER","DEPARTMENT":"POLICE","EMPLOYEE ANNUAL SALARY":"$89646.00","ESTIMATED ANNUAL SALARY MINUS FURLOUGHS":"$89646.00"},{"NAME":"AGUIRRE, JUAN M","JOB TITLE":"POLICE OFFICER","DEPARTMENT":"POLICE","EMPLOYEE ANNUAL SALARY":"$83916.00","ESTIMATED ANNUAL SALARY MINUS FURLOUGHS":"$83916.00"},{"NAME":"AGUIRRE, PABLO","JOB TITLE":"POLICE OFFICER","DEPARTMENT":"POLICE","EMPLOYEE ANNUAL SALARY":"$71040.00","ESTIMATED ANNUAL SALARY MINUS FURLOUGHS":"$71040.00"},{"NAME":"AGUIRRE, RAMIRO","JOB TITLE":"POLICE OFFICER","DEPARTMENT":"POLICE","EMPLOYEE ANNUAL SALARY":"$74628.00","ESTIMATED ANNUAL SALARY MINUS FURLOUGHS":"$74628.00"},{"NAME":"AGUIRRE, ROBERT J","JOB TITLE":"LINEMAN","DEPARTMENT":"TRANSPORTN","EMPLOYEE ANNUAL SALARY":"$84968.00","ESTIMATED ANNUAL SALARY MINUS FURLOUGHS":"$77480.00"},{"NAME":"AGUIRRE, TANYA L","JOB TITLE":"POLICE OFFICER","DEPARTMENT":"POLICE","EMPLOYEE ANNUAL SALARY":"$82878.00","ESTIMATED ANNUAL SALARY MINUS FURLOUGHS":"$82878.00"},{"NAME":"AGYEKUM, KOFI","JOB TITLE":"PROGRAMMER\/ANALYST","DEPARTMENT":"BUSINESS AFFAIRS","EMPLOYEE ANNUAL SALARY":"$80808.00","ESTIMATED ANNUAL SALARY MINUS FURLOUGHS":"$80808.00"},{"NAME":"AHARANWA, ALEXANDER E","JOB TITLE":"HELP DESK TECHNICIAN","DEPARTMENT":"PUBLIC LIBRARY","EMPLOYEE ANNUAL SALARY":"$61308.00","ESTIMATED ANNUAL SALARY MINUS FURLOUGHS":"$61308.00"},{"NAME":"AHEARN, DORY E","JOB TITLE":"POLICE OFFICER","DEPARTMENT":"POLICE","EMPLOYEE ANNUAL SALARY":"$79926.00","ESTIMATED ANNUAL SALARY MINUS FURLOUGHS":"$79926.00"},{"NAME":"AHERN, LAWRENCE J","JOB TITLE":"LIEUTENANT-EMT","DEPARTMENT":"FIRE","EMPLOYEE ANNUAL SALARY":"$107064.00","ESTIMATED ANNUAL SALARY MINUS FURLOUGHS":"$107064.00"},{"NAME":"AHERN, MICHAEL J","JOB TITLE":"FIRE ENGINEER-EMT","DEPARTMENT":"FIRE","EMPLOYEE ANNUAL SALARY":"$87756.00","ESTIMATED ANNUAL SALARY MINUS FURLOUGHS":"$87756.00"},{"NAME":"AHERN, PATRICIA","JOB TITLE":"ALDERMANIC AIDE","DEPARTMENT":"CITY COUNCIL","EMPLOYEE ANNUAL SALARY":"$22880.00","ESTIMATED ANNUAL SALARY MINUS FURLOUGHS":"$21828.00"},{"NAME":"AHERN, PATRICK J","JOB TITLE":"FIREFIGHTER","DEPARTMENT":"FIRE","EMPLOYEE ANNUAL SALARY":"$77238.00","ESTIMATED ANNUAL SALARY MINUS FURLOUGHS":"$77238.00"},{"NAME":"AHERN, SCOTT E","JOB TITLE":"POLICE OFFICER","DEPARTMENT":"POLICE","EMPLOYEE ANNUAL SALARY":"$79926.00","ESTIMATED ANNUAL SALARY MINUS FURLOUGHS":"$79926.00"},{"NAME":"AHLFELD, DANIEL","JOB TITLE":"FIREFIGHTER-EMT","DEPARTMENT":"FIRE","EMPLOYEE ANNUAL SALARY":"$78354.00","ESTIMATED ANNUAL SALARY MINUS FURLOUGHS":"$78354.00"},{"NAME":"AHLHEIM, MARGARET L","JOB TITLE":"FIREFIGHTER-EMT","DEPARTMENT":"FIRE","EMPLOYEE ANNUAL SALARY":"$81096.00","ESTIMATED ANNUAL SALARY MINUS FURLOUGHS":"$81096.00"},{"NAME":"AHMAD, AMER","JOB TITLE":"CITY COMPTROLLER","DEPARTMENT":"FINANCE","EMPLOYEE ANNUAL SALARY":"$165000.00","ESTIMATED ANNUAL SALARY MINUS FURLOUGHS":"$149828.00"},{"NAME":"AHMAD, FADI M","JOB TITLE":"POLICE OFFICER","DEPARTMENT":"POLICE","EMPLOYEE ANNUAL SALARY":"$74628.00","ESTIMATED ANNUAL SALARY MINUS FURLOUGHS":"$74628.00"},{"NAME":"AHMAD, FAROOQ","JOB TITLE":"LABORER","DEPARTMENT":"AVIATION","EMPLOYEE ANNUAL SALARY":"$61506.00","ESTIMATED ANNUAL SALARY MINUS FURLOUGHS":"$56086.00"},{"NAME":"AHMAD, MARYAM","JOB TITLE":"SEXUAL HARASSMENT OFFICER","DEPARTMENT":"HUMAN RESOURCES","EMPLOYEE ANNUAL SALARY":"$98436.00","ESTIMATED ANNUAL SALARY MINUS FURLOUGHS":"$89384.00"},{"NAME":"AHMAD, SARWAT","JOB TITLE":"LIBRARY CLERK - HOURLY","DEPARTMENT":"PUBLIC LIBRARY","EMPLOYEE ANNUAL SALARY":"$14706.00","ESTIMATED ANNUAL SALARY MINUS FURLOUGHS":"$14706.00"},{"NAME":"AHMADIAN, PETER A","JOB TITLE":"ASST CORPORATION COUNSEL","DEPARTMENT":"LAW","EMPLOYEE ANNUAL SALARY":"$61980.00","ESTIMATED ANNUAL SALARY MINUS FURLOUGHS":"$56281.00"},{"NAME":"AHMED, HAROON M","JOB TITLE":"FINANCE OFFICER","DEPARTMENT":"HEALTH","EMPLOYEE ANNUAL SALARY":"$80256.00","ESTIMATED ANNUAL SALARY MINUS FURLOUGHS":"$72876.00"},{"NAME":"AHMED, KHALID","JOB TITLE":"CHIEF PROGRAMMER\/ANALYST","DEPARTMENT":"WATER MGMNT","EMPLOYEE ANNUAL SALARY":"$110352.00","ESTIMATED ANNUAL SALARY MINUS FURLOUGHS":"$100205.00"},{"NAME":"AHMED, MOHAMMAD A","JOB TITLE":"PARKING ENFORCEMENT AIDE","DEPARTMENT":"REVENUE","EMPLOYEE ANNUAL SALARY":"$46656.00","ESTIMATED ANNUAL SALARY MINUS FURLOUGHS":"$44690.00"},{"NAME":"AHMED, NAFEES","JOB TITLE":"DEPUTY COMMISSIONER","DEPARTMENT":"AVIATION","EMPLOYEE ANNUAL SALARY":"$116904.00","ESTIMATED ANNUAL SALARY MINUS FURLOUGHS":"$106154.00"},{"NAME":"AHMED, QUAZI S","JOB TITLE":"CRIMINAL HISTORY ANALYST","DEPARTMENT":"POLICE","EMPLOYEE ANNUAL SALARY":"$70464.00","ESTIMATED ANNUAL SALARY MINUS FURLOUGHS":"$70464.00"},{"NAME":"AHMED, RIZWANA P","JOB TITLE":"SENIOR RESEARCH ANALYST","DEPARTMENT":"COMMUNITY DEVELOPMENT","EMPLOYEE ANNUAL SALARY":"$73932.00","ESTIMATED ANNUAL SALARY MINUS FURLOUGHS":"$73932.00"},{"NAME":"AHMED, SHAHRUKH Z","JOB TITLE":"CUSTOMER ACCOUNT REP - PER AGRMNT","DEPARTMENT":"REVENUE","EMPLOYEE ANNUAL SALARY":"$24079.00","ESTIMATED ANNUAL SALARY MINUS FURLOUGHS":"$24079.00"},{"NAME":"AHRENS, JOHN E","JOB TITLE":"LIEUTENANT-EMT","DEPARTMENT":"FIRE","EMPLOYEE ANNUAL SALARY":"$107064.00","ESTIMATED ANNUAL SALARY MINUS FURLOUGHS":"$107064.00"},{"NAME":"AICH, ABRAHAM A","JOB TITLE":"POLICE OFFICER","DEPARTMENT":"POLICE","EMPLOYEE ANNUAL SALARY":"$77238.00","ESTIMATED ANNUAL SALARY MINUS FURLOUGHS":"$77238.00"},{"NAME":"AIKENS, BRADLEY K","JOB TITLE":"LIEUTENANT","DEPARTMENT":"FIRE","EMPLOYEE ANNUAL SALARY":"$98766.00","ESTIMATED ANNUAL SALARY MINUS FURLOUGHS":"$98766.00"},{"NAME":"AIKENS, CATHERINE","JOB TITLE":"PERSONAL COMPUTER OPERATOR I","DEPARTMENT":"POLICE","EMPLOYEE ANNUAL SALARY":"$42264.00","ESTIMATED ANNUAL SALARY MINUS FURLOUGHS":"$42264.00"},{"NAME":"AIKENS, CLORA M","JOB TITLE":"PUBLIC HEALTH NURSE IV","DEPARTMENT":"HEALTH","EMPLOYEE ANNUAL SALARY":"$96264.00","ESTIMATED ANNUAL SALARY MINUS FURLOUGHS":"$96264.00"},{"NAME":"AIKENS, JANET S","JOB TITLE":"MEDICAL X-RAY TECHNOLOGIST","DEPARTMENT":"HEALTH","EMPLOYEE ANNUAL SALARY":"$52824.00","ESTIMATED ANNUAL SALARY MINUS FURLOUGHS":"$52824.00"},{"NAME":"AIKIN JR, LAWRENCE J","JOB TITLE":"POLICE OFFICER","DEPARTMENT":"POLICE","EMPLOYEE ANNUAL SALARY":"$77238.00","ESTIMATED ANNUAL SALARY MINUS FURLOUGHS":"$77238.00"},{"NAME":"AILLON, EDMUNDO R","JOB TITLE":"POLICE OFFICER","DEPARTMENT":"POLICE","EMPLOYEE ANNUAL SALARY":"$77238.00","ESTIMATED ANNUAL SALARY MINUS FURLOUGHS":"$77238.00"},{"NAME":"AINUDDIN, ZAHID N","JOB TITLE":"MOTOR TRUCK DRIVER","DEPARTMENT":"STREETS & SAN","EMPLOYEE ANNUAL SALARY":"$70408.00","ESTIMATED ANNUAL SALARY MINUS FURLOUGHS":"$70408.00"},{"NAME":"AJAYI, HAZIZ A","JOB TITLE":"AUDITOR III","DEPARTMENT":"COMPLIANCE","EMPLOYEE ANNUAL SALARY":"$88140.00","ESTIMATED ANNUAL SALARY MINUS FURLOUGHS":"$88140.00"},{"NAME":"AJAYI, VICTORIA","JOB TITLE":"FOSTER GRANDPARENT","DEPARTMENT":"FAMILY & SUPPORT","EMPLOYEE ANNUAL SALARY":"$2756.00","ESTIMATED ANNUAL SALARY MINUS FURLOUGHS":"$2756.00"},{"NAME":"AJZYK, EDWARD G","JOB TITLE":"CHIEF CLERK - ELECTIONS","DEPARTMENT":"BOARD OF ELECTION","EMPLOYEE ANNUAL SALARY":"$66648.00","ESTIMATED ANNUAL SALARY MINUS FURLOUGHS":"$60519.00"},{"NAME":"AKANA, MARK S","JOB TITLE":"POLICE OFFICER","DEPARTMENT":"POLICE","EMPLOYEE ANNUAL SALARY":"$82878.00","ESTIMATED ANNUAL SALARY MINUS FURLOUGHS":"$82878.00"},{"NAME":"AKERS, AMY A","JOB TITLE":"EXECUTIVE SECRETARY I","DEPARTMENT":"LAW","EMPLOYEE ANNUAL SALARY":"$45684.00","ESTIMATED ANNUAL SALARY MINUS FURLOUGHS":"$41483.00"},{"NAME":"AKERS, DEREC A","JOB TITLE":"FIREFIGHTER","DEPARTMENT":"FIRE","EMPLOYEE ANNUAL SALARY":"$77238.00","ESTIMATED ANNUAL SALARY MINUS FURLOUGHS":"$77238.00"},{"NAME":"AKERSON, WILLIE L","JOB TITLE":"POLICE OFFICER","DEPARTMENT":"POLICE","EMPLOYEE ANNUAL SALARY":"$79926.00","ESTIMATED ANNUAL SALARY MINUS FURLOUGHS":"$79926.00"},{"NAME":"AKHTAR, SAEED","JOB TITLE":"ASST CITY TREASURER","DEPARTMENT":"TREASURER","EMPLOYEE ANNUAL SALARY":"$85020.00","ESTIMATED ANNUAL SALARY MINUS FURLOUGHS":"$77202.00"},{"NAME":"AKINBUSUYI, AYOKUNLE","JOB TITLE":"POLICE OFFICER","DEPARTMENT":"POLICE","EMPLOYEE ANNUAL SALARY":"$71040.00","ESTIMATED ANNUAL SALARY MINUS FURLOUGHS":"$71040.00"},{"NAME":"AKINS, DARYL","JOB TITLE":"POLICE OFFICER","DEPARTMENT":"POLICE","EMPLOYEE ANNUAL SALARY":"$85278.00","ESTIMATED ANNUAL SALARY MINUS FURLOUGHS":"$85278.00"},{"NAME":"AKINS, KIMBERLY L","JOB TITLE":"POLICE OFFICER","DEPARTMENT":"POLICE","EMPLOYEE ANNUAL SALARY":"$74628.00","ESTIMATED ANNUAL SALARY MINUS FURLOUGHS":"$74628.00"},{"NAME":"AKINS, LISA","JOB TITLE":"SANITATION LABORER","DEPARTMENT":"STREETS & SAN","EMPLOYEE ANNUAL SALARY":"$65894.00","ESTIMATED ANNUAL SALARY MINUS FURLOUGHS":"$60088.00"},{"NAME":"AKINS, LOU ANN","JOB TITLE":"POOL MOTOR TRUCK DRIVER","DEPARTMENT":"TRANSPORTN","EMPLOYEE ANNUAL SALARY":"$70408.00","ESTIMATED ANNUAL SALARY MINUS FURLOUGHS":"$70408.00"},{"NAME":"AKINS, MONICA E","JOB TITLE":"POLICE OFFICER","DEPARTMENT":"POLICE","EMPLOYEE ANNUAL SALARY":"$71040.00","ESTIMATED ANNUAL SALARY MINUS FURLOUGHS":"$71040.00"},{"NAME":"AKINS, ROBIN G","JOB TITLE":"POLICE OFFICER","DEPARTMENT":"POLICE","EMPLOYEE ANNUAL SALARY":"$74628.00","ESTIMATED ANNUAL SALARY MINUS FURLOUGHS":"$74628.00"},{"NAME":"AKUAMOAH, BESSIE S","JOB TITLE":"PROGRAM DIR","DEPARTMENT":"HEALTH","EMPLOYEE ANNUAL SALARY":"$69684.00","ESTIMATED ANNUAL SALARY MINUS FURLOUGHS":"$63276.00"},{"NAME":"AL AMIN, HASAN M","JOB TITLE":"POLICE OFFICER","DEPARTMENT":"POLICE","EMPLOYEE ANNUAL SALARY":"$79926.00","ESTIMATED ANNUAL SALARY MINUS FURLOUGHS":"$79926.00"},{"NAME":"AL AMIN, HASSAN","JOB TITLE":"POLICE OFFICER","DEPARTMENT":"POLICE","EMPLOYEE ANNUAL SALARY":"$79926.00","ESTIMATED ANNUAL SALARY MINUS FURLOUGHS":"$79926.00"},{"NAME":"AL AMIN, MAHASIN I","JOB TITLE":"COMMUNICABLE DISEASE CONTROL INVESTIGATOR II","DEPARTMENT":"HEALTH","EMPLOYEE ANNUAL SALARY":"$67296.00","ESTIMATED ANNUAL SALARY MINUS FURLOUGHS":"$67296.00"},{"NAME":"AL FARAH, TENA A","JOB TITLE":"POLICE CADET","DEPARTMENT":"POLICE","EMPLOYEE ANNUAL SALARY":"$9360.00","ESTIMATED ANNUAL SALARY MINUS FURLOUGHS":"$9360.00"},{"NAME":"AL GHOLEH, HASAN M","JOB TITLE":"PROJECT MANAGER - BUILDINGS","DEPARTMENT":"BUILDINGS","EMPLOYEE ANNUAL SALARY":"$96276.00","ESTIMATED ANNUAL SALARY MINUS FURLOUGHS":"$96276.00"},{"NAME":"AL HAJJE, MOHAMAD H","JOB TITLE":"FILTRATION ENGINEER IV","DEPARTMENT":"WATER MGMNT","EMPLOYEE ANNUAL SALARY":"$96276.00","ESTIMATED ANNUAL SALARY MINUS FURLOUGHS":"$96276.00"},{"NAME":"ALAGNA, ANTHONY J","JOB TITLE":"POLICE COMMUNICATIONS OPERATOR I","DEPARTMENT":"OEMC","EMPLOYEE ANNUAL SALARY":"$61692.00","ESTIMATED ANNUAL SALARY MINUS FURLOUGHS":"$59092.00"},{"NAME":"ALAGNA, STEVEN O","JOB TITLE":"POLICE OFFICER","DEPARTMENT":"POLICE","EMPLOYEE ANNUAL SALARY":"$79926.00","ESTIMATED ANNUAL SALARY MINUS FURLOUGHS":"$79926.00"},{"NAME":"ALAM, MOHAMMAD H","JOB TITLE":"WATER CHEMIST IV","DEPARTMENT":"WATER MGMNT","EMPLOYEE ANNUAL SALARY":"$88140.00","ESTIMATED ANNUAL SALARY MINUS FURLOUGHS":"$88140.00"},{"NAME":"ALAM, SYED S","JOB TITLE":"ACCOUNTANT II","DEPARTMENT":"REVENUE","EMPLOYEE ANNUAL SALARY":"$73932.00","ESTIMATED ANNUAL SALARY MINUS FURLOUGHS":"$73932.00"},{"NAME":"ALAMILLO, ARMANDO","JOB TITLE":"POLICE OFFICER","DEPARTMENT":"POLICE","EMPLOYEE ANNUAL SALARY":"$67704.00","ESTIMATED ANNUAL SALARY MINUS FURLOUGHS":"$67704.00"},{"NAME":"ALAMO, ROBERTO G","JOB TITLE":"FIREFIGHTER","DEPARTMENT":"FIRE","EMPLOYEE ANNUAL SALARY":"$74628.00","ESTIMATED ANNUAL SALARY MINUS FURLOUGHS":"$74628.00"},{"NAME":"ALANIS, JESUS","JOB TITLE":"PROJECT MANAGER","DEPARTMENT":"HUMAN RESOURCES","EMPLOYEE ANNUAL SALARY":"$80904.00","ESTIMATED ANNUAL SALARY MINUS FURLOUGHS":"$73465.00"},{"NAME":"ALANIS, JOSE E","JOB TITLE":"POLICE OFFICER","DEPARTMENT":"POLICE","EMPLOYEE ANNUAL SALARY":"$86508.00","ESTIMATED ANNUAL SALARY MINUS FURLOUGHS":"$86508.00"},{"NAME":"ALANIS, OSCAR","JOB TITLE":"MACHINIST (AUTOMOTIVE)","DEPARTMENT":"FLEET MANAGEMNT","EMPLOYEE ANNUAL SALARY":"$89773.00","ESTIMATED ANNUAL SALARY MINUS FURLOUGHS":"$81862.00"},{"NAME":"ALANIS, ROBERT","JOB TITLE":"POLICE OFFICER","DEPARTMENT":"POLICE","EMPLOYEE ANNUAL SALARY":"$79926.00","ESTIMATED ANNUAL SALARY MINUS FURLOUGHS":"$79926.00"},{"NAME":"ALANIZ, ARTHUR P","JOB TITLE":"POLICE OFFICER","DEPARTMENT":"POLICE","EMPLOYEE ANNUAL SALARY":"$89646.00","ESTIMATED ANNUAL SALARY MINUS FURLOUGHS":"$89646.00"},{"NAME":"ALANIZ, BRIAN","JOB TITLE":"POLICE OFFICER","DEPARTMENT":"POLICE","EMPLOYEE ANNUAL SALARY":"$74628.00","ESTIMATED ANNUAL SALARY MINUS FURLOUGHS":"$74628.00"},{"NAME":"ALANIZ, CORA","JOB TITLE":"CUSTODIAL WORKER","DEPARTMENT":"AVIATION","EMPLOYEE ANNUAL SALARY":"$24752.00","ESTIMATED ANNUAL SALARY MINUS FURLOUGHS":"$24752.00"},{"NAME":"ALANIZ, ELIZABETH","JOB TITLE":"POLICE OFFICER","DEPARTMENT":"POLICE","EMPLOYEE ANNUAL SALARY":"$77238.00","ESTIMATED ANNUAL SALARY MINUS FURLOUGHS":"$77238.00"},{"NAME":"ALANIZ, JOHN E","JOB TITLE":"FIREFIGHTER (PER ARBITRATORS AWARD)","DEPARTMENT":"FIRE","EMPLOYEE ANNUAL SALARY":"$92268.00","ESTIMATED ANNUAL SALARY MINUS FURLOUGHS":"$92268.00"},{"NAME":"ALANIZ, MICHAEL R","JOB TITLE":"POLICE OFFICER","DEPARTMENT":"POLICE","EMPLOYEE ANNUAL SALARY":"$74628.00","ESTIMATED ANNUAL SALARY MINUS FURLOUGHS":"$74628.00"},{"NAME":"ALANIZ, ROBERT A","JOB TITLE":"CUSTODIAL WORKER","DEPARTMENT":"AVIATION","EMPLOYEE ANNUAL SALARY":"$38584.00","ESTIMATED ANNUAL SALARY MINUS FURLOUGHS":"$35184.00"},{"NAME":"ALANIZ, SANDRA","JOB TITLE":"SUPERVISING CLERK","DEPARTMENT":"FAMILY & SUPPORT","EMPLOYEE ANNUAL SALARY":"$55872.00","ESTIMATED ANNUAL SALARY MINUS FURLOUGHS":"$55872.00"},{"NAME":"ALANZO, SHARON","JOB TITLE":"PUBLIC HEALTH NURSE I","DEPARTMENT":"HEALTH","EMPLOYEE ANNUAL SALARY":"$84420.00","ESTIMATED ANNUAL SALARY MINUS FURLOUGHS":"$84420.00"},{"NAME":"ALARCON, LUIS J","JOB TITLE":"LOAN PROCESSING SPECIALIST","DEPARTMENT":"COMMUNITY DEVELOPMENT","EMPLOYEE ANNUAL SALARY":"$67296.00","ESTIMATED ANNUAL SALARY MINUS FURLOUGHS":"$67296.00"},{"NAME":"ALATORRE, FRANK J","JOB TITLE":"POLICE OFFICER","DEPARTMENT":"POLICE","EMPLOYEE ANNUAL SALARY":"$71040.00","ESTIMATED ANNUAL SALARY MINUS FURLOUGHS":"$71040.00"},{"NAME":"ALBA, SAUL B","JOB TITLE":"MOTOR TRUCK DRIVER","DEPARTMENT":"STREETS & SAN","EMPLOYEE ANNUAL SALARY":"$70408.00","ESTIMATED ANNUAL SALARY MINUS FURLOUGHS":"$70408.00"},{"NAME":"ALBARILLO, VERBENA S","JOB TITLE":"PUBLIC HEALTH NUTRITIONIST III","DEPARTMENT":"HEALTH","EMPLOYEE ANNUAL SALARY":"$67308.00","ESTIMATED ANNUAL SALARY MINUS FURLOUGHS":"$61119.00"},{"NAME":"ALBARRAN, ALBERTO S","JOB TITLE":"POLICE OFFICER","DEPARTMENT":"POLICE","EMPLOYEE ANNUAL SALARY":"$79926.00","ESTIMATED ANNUAL SALARY MINUS FURLOUGHS":"$79926.00"},{"NAME":"ALBARRAN, FABIAN","JOB TITLE":"FIREFIGHTER-EMT","DEPARTMENT":"FIRE","EMPLOYEE ANNUAL SALARY":"$78354.00","ESTIMATED ANNUAL SALARY MINUS FURLOUGHS":"$78354.00"},{"NAME":"ALBARRAN, FRANK J","JOB TITLE":"COORDINATING FIRE COMMUNICATIONS OPERATOR","DEPARTMENT":"OEMC","EMPLOYEE ANNUAL SALARY":"$104853.00","ESTIMATED ANNUAL SALARY MINUS FURLOUGHS":"$95613.00"},{"NAME":"ALBARRAN, MARY M","JOB TITLE":"FIELD PAYROLL AUDITOR","DEPARTMENT":"FIRE","EMPLOYEE ANNUAL SALARY":"$73848.00","ESTIMATED ANNUAL SALARY MINUS FURLOUGHS":"$67340.00"},{"NAME":"ALBERTS, DONNA M","JOB TITLE":"REVENUE INVESTIGATOR II","DEPARTMENT":"BUSINESS AFFAIRS","EMPLOYEE ANNUAL SALARY":"$73848.00","ESTIMATED ANNUAL SALARY MINUS FURLOUGHS":"$73848.00"},{"NAME":"ALBERTS, LOUIS","JOB TITLE":"HAND LABORER","DEPARTMENT":"STREETS & SAN","EMPLOYEE ANNUAL SALARY":"$39541.00","ESTIMATED ANNUAL SALARY MINUS FURLOUGHS":"$36056.00"},{"NAME":"ALBERTS, RICHARD A","JOB TITLE":"FIREFIGHTER","DEPARTMENT":"FIRE","EMPLOYEE ANNUAL SALARY":"$79926.00","ESTIMATED ANNUAL SALARY MINUS FURLOUGHS":"$79926.00"},{"NAME":"ALBIN, RAYMOND M","JOB TITLE":"EQUIPMENT DISPATCHER","DEPARTMENT":"FLEET MANAGEMNT","EMPLOYEE ANNUAL SALARY":"$71635.00","ESTIMATED ANNUAL SALARY MINUS FURLOUGHS":"$71635.00"},{"NAME":"ALBRECHT, DANIEL R","JOB TITLE":"MACHINIST (AUTOMOTIVE)","DEPARTMENT":"FLEET MANAGEMNT","EMPLOYEE ANNUAL SALARY":"$89773.00","ESTIMATED ANNUAL SALARY MINUS FURLOUGHS":"$81862.00"},{"NAME":"ALBRECHT, DAWN M","JOB TITLE":"POLICE OFFICER","DEPARTMENT":"POLICE","EMPLOYEE ANNUAL SALARY":"$74628.00","ESTIMATED ANNUAL SALARY MINUS FURLOUGHS":"$74628.00"},{"NAME":"ALBRIGHT, KEITH E","JOB TITLE":"FIREFIGHTER-EMT","DEPARTMENT":"FIRE","EMPLOYEE ANNUAL SALARY":"$81096.00","ESTIMATED ANNUAL SALARY MINUS FURLOUGHS":"$81096.00"},{"NAME":"ALBRITTON, JOSEPH A","JOB TITLE":"DEPUTY COMMISSIONER","DEPARTMENT":"DISABILITIES","EMPLOYEE ANNUAL SALARY":"$93912.00","ESTIMATED ANNUAL SALARY MINUS FURLOUGHS":"$85276.00"},{"NAME":"ALCALA, DAVID A","JOB TITLE":"POLICE OFFICER","DEPARTMENT":"POLICE","EMPLOYEE ANNUAL SALARY":"$74628.00","ESTIMATED ANNUAL SALARY MINUS FURLOUGHS":"$74628.00"},{"NAME":"ALCALA, RUBEN","JOB TITLE":"SANITATION LABORER","DEPARTMENT":"STREETS & SAN","EMPLOYEE ANNUAL SALARY":"$65894.00","ESTIMATED ANNUAL SALARY MINUS FURLOUGHS":"$60088.00"},{"NAME":"ALCANTAR, CELIA","JOB TITLE":"ACCOUNTING TECHNICIAN III","DEPARTMENT":"HEALTH","EMPLOYEE ANNUAL SALARY":"$73848.00","ESTIMATED ANNUAL SALARY MINUS FURLOUGHS":"$73848.00"},{"NAME":"ALCANTARA, ELIZABETH","JOB TITLE":"POLICE COMMUNICATIONS OPERATOR I","DEPARTMENT":"OEMC","EMPLOYEE ANNUAL SALARY":"$56208.00","ESTIMATED ANNUAL SALARY MINUS FURLOUGHS":"$53839.00"},{"NAME":"ALCANTARA, JOVITA L","JOB TITLE":"CROSSING GUARD","DEPARTMENT":"POLICE","EMPLOYEE ANNUAL SALARY":"$15319.00","ESTIMATED ANNUAL SALARY MINUS FURLOUGHS":"$15319.00"},{"NAME":"ALCARAZ, DORIAN L","JOB TITLE":"TIMEKEEPER - CPD","DEPARTMENT":"IPRA","EMPLOYEE ANNUAL SALARY":"$55872.00","ESTIMATED ANNUAL SALARY MINUS FURLOUGHS":"$55872.00"},{"NAME":"ALCAUTER, ELIASARD","JOB TITLE":"FIREFIGHTER-EMT","DEPARTMENT":"FIRE","EMPLOYEE ANNUAL SALARY":"$71082.00","ESTIMATED ANNUAL SALARY MINUS FURLOUGHS":"$71082.00"},{"NAME":"ALCAZAR, ANTOINETTE","JOB TITLE":"POLICE OFFICER","DEPARTMENT":"POLICE","EMPLOYEE ANNUAL SALARY":"$74628.00","ESTIMATED ANNUAL SALARY MINUS FURLOUGHS":"$74628.00"},{"NAME":"ALCAZAR, DAVID E","JOB TITLE":"POLICE OFFICER","DEPARTMENT":"POLICE","EMPLOYEE ANNUAL SALARY":"$74628.00","ESTIMATED ANNUAL SALARY MINUS FURLOUGHS":"$74628.00"},{"NAME":"ALCAZAR, GUADALUPE R","JOB TITLE":"PUBLIC HEALTH NURSE II","DEPARTMENT":"HEALTH","EMPLOYEE ANNUAL SALARY":"$80376.00","ESTIMATED ANNUAL SALARY MINUS FURLOUGHS":"$80376.00"},{"NAME":"ALCAZAR, VICTOR A","JOB TITLE":"POLICE OFFICER","DEPARTMENT":"POLICE","EMPLOYEE ANNUAL SALARY":"$77238.00","ESTIMATED ANNUAL SALARY MINUS FURLOUGHS":"$77238.00"},{"NAME":"ALCORN, RANDOLPH P","JOB TITLE":"ELECTRICAL MECHANIC","DEPARTMENT":"AVIATION","EMPLOYEE ANNUAL SALARY":"$84032.00","ESTIMATED ANNUAL SALARY MINUS FURLOUGHS":"$76627.00"},{"NAME":"ALCOZER, JOSEPH","JOB TITLE":"LINEMAN","DEPARTMENT":"TRANSPORTN","EMPLOYEE ANNUAL SALARY":"$84968.00","ESTIMATED ANNUAL SALARY MINUS FURLOUGHS":"$77480.00"},{"NAME":"ALCOZER, WILLIAM","JOB TITLE":"LINEMAN","DEPARTMENT":"TRANSPORTN","EMPLOYEE ANNUAL SALARY":"$84968.00","ESTIMATED ANNUAL SALARY MINUS FURLOUGHS":"$77480.00"},{"NAME":"ALDAHONDO, GIL A","JOB TITLE":"POLICE OFFICER","DEPARTMENT":"POLICE","EMPLOYEE ANNUAL SALARY":"$74628.00","ESTIMATED ANNUAL SALARY MINUS FURLOUGHS":"$74628.00"},{"NAME":"ALDANA, BERTA","JOB TITLE":"PUBLIC HEALTH NURSE I","DEPARTMENT":"HEALTH","EMPLOYEE ANNUAL SALARY":"$76476.00","ESTIMATED ANNUAL SALARY MINUS FURLOUGHS":"$76476.00"},{"NAME":"ALDANA, CARLOS J","JOB TITLE":"POLICE OFFICER","DEPARTMENT":"POLICE","EMPLOYEE ANNUAL SALARY":"$77238.00","ESTIMATED ANNUAL SALARY MINUS FURLOUGHS":"$77238.00"},{"NAME":"ALDARONDO AGUIRRE, DELIA","JOB TITLE":"MOTOR TRUCK DRIVER","DEPARTMENT":"WATER MGMNT","EMPLOYEE ANNUAL SALARY":"$70408.00","ESTIMATED ANNUAL SALARY MINUS FURLOUGHS":"$70408.00"},{"NAME":"ALDAY, MARTHA S","JOB TITLE":"POLICE OFFICER","DEPARTMENT":"POLICE","EMPLOYEE ANNUAL SALARY":"$82878.00","ESTIMATED ANNUAL SALARY MINUS FURLOUGHS":"$82878.00"},{"NAME":"ALDER, GERALD H","JOB TITLE":"ASST TO THE MAYOR","DEPARTMENT":"MAYOR'S OFFICE","EMPLOYEE ANNUAL SALARY":"$63516.00","ESTIMATED ANNUAL SALARY MINUS FURLOUGHS":"$57675.00"},{"NAME":"ALDERDEN, JACOB M","JOB TITLE":"SERGEANT","DEPARTMENT":"POLICE","EMPLOYEE ANNUAL SALARY":"$92778.00","ESTIMATED ANNUAL SALARY MINUS FURLOUGHS":"$92778.00"},{"NAME":"ALDRICH, JEFFREY S","JOB TITLE":"POLICE OFFICER","DEPARTMENT":"POLICE","EMPLOYEE ANNUAL SALARY":"$86508.00","ESTIMATED ANNUAL SALARY MINUS FURLOUGHS":"$86508.00"},{"NAME":"ALDRIDGE, JENNIFER L","JOB TITLE":"POLICE OFFICER","DEPARTMENT":"POLICE","EMPLOYEE ANNUAL SALARY":"$82878.00","ESTIMATED ANNUAL SALARY MINUS FURLOUGHS":"$82878.00"},{"NAME":"ALDUGOM, NABIL K","JOB TITLE":"SANITATION LABORER","DEPARTMENT":"STREETS & SAN","EMPLOYEE ANNUAL SALARY":"$65894.00","ESTIMATED ANNUAL SALARY MINUS FURLOUGHS":"$60088.00"},{"NAME":"ALDWORTH, JAMES P","JOB TITLE":"FIREFIGHTER","DEPARTMENT":"FIRE","EMPLOYEE ANNUAL SALARY":"$77238.00","ESTIMATED ANNUAL SALARY MINUS FURLOUGHS":"$77238.00"},{"NAME":"ALEBICH, GERALYN A","JOB TITLE":"LEGISLATIVE AIDE","DEPARTMENT":"CITY COUNCIL","EMPLOYEE ANNUAL SALARY":"$40000.00","ESTIMATED ANNUAL SALARY MINUS FURLOUGHS":"$36322.00"},{"NAME":"ALEGADO, ROBERTO S","JOB TITLE":"POLICE OFFICER","DEPARTMENT":"POLICE","EMPLOYEE ANNUAL SALARY":"$77238.00","ESTIMATED ANNUAL SALARY MINUS FURLOUGHS":"$77238.00"},{"NAME":"ALEGARBES, MARIETTA L","JOB TITLE":"PUBLIC HEALTH NURSE I","DEPARTMENT":"HEALTH","EMPLOYEE ANNUAL SALARY":"$80376.00","ESTIMATED ANNUAL SALARY MINUS FURLOUGHS":"$80376.00"},{"NAME":"ALEJANDRE, ROCKY J","JOB TITLE":"MOTOR TRUCK DRIVER","DEPARTMENT":"TRANSPORTN","EMPLOYEE ANNUAL SALARY":"$70408.00","ESTIMATED ANNUAL SALARY MINUS FURLOUGHS":"$70408.00"},{"NAME":"ALEJO, LUIS F","JOB TITLE":"POLICE OFFICER","DEPARTMENT":"POLICE","EMPLOYEE ANNUAL SALARY":"$79926.00","ESTIMATED ANNUAL SALARY MINUS FURLOUGHS":"$79926.00"},{"NAME":"ALEMAN, GEORGE","JOB TITLE":"FIREFIGHTER-EMT","DEPARTMENT":"FIRE","EMPLOYEE ANNUAL SALARY":"$78354.00","ESTIMATED ANNUAL SALARY MINUS FURLOUGHS":"$78354.00"},{"NAME":"ALEQUIN, ANA I","JOB TITLE":"PROPERTY CUSTODIAN","DEPARTMENT":"POLICE","EMPLOYEE ANNUAL SALARY":"$58548.00","ESTIMATED ANNUAL SALARY MINUS FURLOUGHS":"$58548.00"},{"NAME":"ALESIA, MICHAEL J","JOB TITLE":"POLICE OFFICER","DEPARTMENT":"POLICE","EMPLOYEE ANNUAL SALARY":"$74628.00","ESTIMATED ANNUAL SALARY MINUS FURLOUGHS":"$74628.00"},{"NAME":"ALESSI, CHRISTINE L","JOB TITLE":"POLICE OFFICER","DEPARTMENT":"POLICE","EMPLOYEE ANNUAL SALARY":"$74628.00","ESTIMATED ANNUAL SALARY MINUS FURLOUGHS":"$74628.00"},{"NAME":"ALESZCZYK, ADAM S","JOB TITLE":"POLICE OFFICER","DEPARTMENT":"POLICE","EMPLOYEE ANNUAL SALARY":"$74628.00","ESTIMATED ANNUAL SALARY MINUS FURLOUGHS":"$74628.00"},{"NAME":"ALEXA, MICHELENE A","JOB TITLE":"SERGEANT","DEPARTMENT":"POLICE","EMPLOYEE ANNUAL SALARY":"$95694.00","ESTIMATED ANNUAL SALARY MINUS FURLOUGHS":"$95694.00"},{"NAME":"ALEXANDER JR, GENE I","JOB TITLE":"POLICE OFFICER","DEPARTMENT":"POLICE","EMPLOYEE ANNUAL SALARY":"$77238.00","ESTIMATED ANNUAL SALARY MINUS FURLOUGHS":"$77238.00"},{"NAME":"ALEXANDER, ANGELA","JOB TITLE":"TRAFFIC CONTROL AIDE-HOURLY","DEPARTMENT":"OEMC","EMPLOYEE ANNUAL SALARY":"$18886.00","ESTIMATED ANNUAL SALARY MINUS FURLOUGHS":"$18886.00"},{"NAME":"ALEXANDER, BRENDA","JOB TITLE":"CROSSING GUARD","DEPARTMENT":"POLICE","EMPLOYEE ANNUAL SALARY":"$21268.00","ESTIMATED ANNUAL SALARY MINUS FURLOUGHS":"$21268.00"},{"NAME":"ALEXANDER, CLEMMIE","JOB TITLE":"LABORER","DEPARTMENT":"TRANSPORTN","EMPLOYEE ANNUAL SALARY":"$73216.00","ESTIMATED ANNUAL SALARY MINUS FURLOUGHS":"$66764.00"},{"NAME":"ALEXANDER, CONRAD E","JOB TITLE":"POLICE OFFICER","DEPARTMENT":"POLICE","EMPLOYEE ANNUAL SALARY":"$86508.00","ESTIMATED ANNUAL SALARY MINUS FURLOUGHS":"$86508.00"},{"NAME":"ALEXANDER, DANA","JOB TITLE":"DEPUTY CHIEF","DEPARTMENT":"POLICE","EMPLOYEE ANNUAL SALARY":"$162012.00","ESTIMATED ANNUAL SALARY MINUS FURLOUGHS":"$147114.00"},{"NAME":"ALEXANDER, DARIUS Q","JOB TITLE":"POLICE OFFICER","DEPARTMENT":"POLICE","EMPLOYEE ANNUAL SALARY":"$74628.00","ESTIMATED ANNUAL SALARY MINUS FURLOUGHS":"$74628.00"},{"NAME":"ALEXANDER, DARLENE","JOB TITLE":"POLICE OFFICER","DEPARTMENT":"POLICE","EMPLOYEE ANNUAL SALARY":"$77238.00","ESTIMATED ANNUAL SALARY MINUS FURLOUGHS":"$77238.00"},{"NAME":"ALEXANDER, DEOLA","JOB TITLE":"POLICE OFFICER","DEPARTMENT":"POLICE","EMPLOYEE ANNUAL SALARY":"$79926.00","ESTIMATED ANNUAL SALARY MINUS FURLOUGHS":"$79926.00"},{"NAME":"ALEXANDER, DORIS A","JOB TITLE":"CROSSING GUARD","DEPARTMENT":"POLICE","EMPLOYEE ANNUAL SALARY":"$16806.00","ESTIMATED ANNUAL SALARY MINUS FURLOUGHS":"$16806.00"},{"NAME":"ALEXANDER, EARL","JOB TITLE":"DETENTION AIDE","DEPARTMENT":"POLICE","EMPLOYEE ANNUAL SALARY":"$58860.00","ESTIMATED ANNUAL SALARY MINUS FURLOUGHS":"$56379.00"},{"NAME":"ALEXANDER, HENRY E","JOB TITLE":"SEWER BRICKLAYER","DEPARTMENT":"WATER MGMNT","EMPLOYEE ANNUAL SALARY":"$81182.00","ESTIMATED ANNUAL SALARY MINUS FURLOUGHS":"$74028.00"},{"NAME":"ALEXANDER, JAMES P","JOB TITLE":"AMBULANCE COMMANDER","DEPARTMENT":"FIRE","EMPLOYEE ANNUAL SALARY":"$107820.00","ESTIMATED ANNUAL SALARY MINUS FURLOUGHS":"$107820.00"},{"NAME":"ALEXANDER, KIMBERLY T","JOB TITLE":"POLICE OFFICER","DEPARTMENT":"POLICE","EMPLOYEE ANNUAL SALARY":"$79926.00","ESTIMATED ANNUAL SALARY MINUS FURLOUGHS":"$79926.00"},{"NAME":"ALEXANDER, LARRON H","JOB TITLE":"POLICE OFFICER","DEPARTMENT":"POLICE","EMPLOYEE ANNUAL SALARY":"$74628.00","ESTIMATED ANNUAL SALARY MINUS FURLOUGHS":"$74628.00"},{"NAME":"ALEXANDER, LAVERN","JOB TITLE":"FIREFIGHTER","DEPARTMENT":"FIRE","EMPLOYEE ANNUAL SALARY":"$86460.00","ESTIMATED ANNUAL SALARY MINUS FURLOUGHS":"$86460.00"},{"NAME":"ALEXANDER, LORIE J","JOB TITLE":"CROSSING GUARD","DEPARTMENT":"POLICE","EMPLOYEE ANNUAL SALARY":"$15319.00","ESTIMATED ANNUAL SALARY MINUS FURLOUGHS":"$15319.00"},{"NAME":"ALEXANDER, MARCIA","JOB TITLE":"SUPERVISING CROSSING GUARD","DEPARTMENT":"POLICE","EMPLOYEE ANNUAL SALARY":"$67224.00","ESTIMATED ANNUAL SALARY MINUS FURLOUGHS":"$61042.00"},{"NAME":"ALEXANDER, MARK A","JOB TITLE":"SANITATION LABORER","DEPARTMENT":"STREETS & SAN","EMPLOYEE ANNUAL SALARY":"$65894.00","ESTIMATED ANNUAL SALARY MINUS FURLOUGHS":"$60088.00"},{"NAME":"ALEXANDER, MARY F","JOB TITLE":"FOSTER GRANDPARENT","DEPARTMENT":"FAMILY & SUPPORT","EMPLOYEE ANNUAL SALARY":"$2756.00","ESTIMATED ANNUAL SALARY MINUS FURLOUGHS":"$2756.00"},{"NAME":"ALEXANDER, MICHAEL A","JOB TITLE":"CAPTAIN","DEPARTMENT":"POLICE","EMPLOYEE ANNUAL SALARY":"$124542.00","ESTIMATED ANNUAL SALARY MINUS FURLOUGHS":"$124542.00"},{"NAME":"ALEXANDER, PATRICIA A","JOB TITLE":"WARRANT AND EXTRADITION AIDE","DEPARTMENT":"POLICE","EMPLOYEE ANNUAL SALARY":"$67296.00","ESTIMATED ANNUAL SALARY MINUS FURLOUGHS":"$67296.00"},{"NAME":"ALEXANDER, PERCY","JOB TITLE":"POLICE OFFICER","DEPARTMENT":"POLICE","EMPLOYEE ANNUAL SALARY":"$77238.00","ESTIMATED ANNUAL SALARY MINUS FURLOUGHS":"$77238.00"},{"NAME":"ALEXANDER, ROBERT","JOB TITLE":"SENIOR COMPANION","DEPARTMENT":"FAMILY & SUPPORT","EMPLOYEE ANNUAL SALARY":"$2756.00","ESTIMATED ANNUAL SALARY MINUS FURLOUGHS":"$2756.00"},{"NAME":"ALEXANDER, ROCHELLE D","JOB TITLE":"CROSSING GUARD","DEPARTMENT":"POLICE","EMPLOYEE ANNUAL SALARY":"$17618.00","ESTIMATED ANNUAL SALARY MINUS FURLOUGHS":"$17618.00"},{"NAME":"ALEXANDER, ROSS J","JOB TITLE":"POLICE OFFICER","DEPARTMENT":"POLICE","EMPLOYEE ANNUAL SALARY":"$74628.00","ESTIMATED ANNUAL SALARY MINUS FURLOUGHS":"$74628.00"},{"NAME":"ALEXANDER, SAMUEL M","JOB TITLE":"ASST DISTRICT SUPERINTENDENT","DEPARTMENT":"WATER MGMNT","EMPLOYEE ANNUAL SALARY":"$97760.00","ESTIMATED ANNUAL SALARY MINUS FURLOUGHS":"$89145.00"},{"NAME":"ALEXANDER, SAMUEL M","JOB TITLE":"FIELD SERVICE SPECIALIST III","DEPARTMENT":"TRANSPORTN","EMPLOYEE ANNUAL SALARY":"$73848.00","ESTIMATED ANNUAL SALARY MINUS FURLOUGHS":"$67340.00"},{"NAME":"ALEXANDER, STEVE","JOB TITLE":"HAND LABORER","DEPARTMENT":"STREETS & SAN","EMPLOYEE ANNUAL SALARY":"$39541.00","ESTIMATED ANNUAL SALARY MINUS FURLOUGHS":"$36056.00"},{"NAME":"ALEXANDER, TOM","JOB TITLE":"DEPUTY PRESS SECRETARY","DEPARTMENT":"MAYOR'S OFFICE","EMPLOYEE ANNUAL SALARY":"$96000.00","ESTIMATED ANNUAL SALARY MINUS FURLOUGHS":"$87172.00"},{"NAME":"ALEXANDER, VERONICA J","JOB TITLE":"HAND LABORER","DEPARTMENT":"STREETS & SAN","EMPLOYEE ANNUAL SALARY":"$39541.00","ESTIMATED ANNUAL SALARY MINUS FURLOUGHS":"$36056.00"},{"NAME":"ALEXANDER, WENDY R","JOB TITLE":"TESTING ADMINISTRATOR","DEPARTMENT":"HUMAN RESOURCES","EMPLOYEE ANNUAL SALARY":"$62964.00","ESTIMATED ANNUAL SALARY MINUS FURLOUGHS":"$57174.00"},{"NAME":"ALEXANDER-FALLO, JULIE E","JOB TITLE":"POLICE OFFICER","DEPARTMENT":"POLICE","EMPLOYEE ANNUAL SALARY":"$82878.00","ESTIMATED ANNUAL SALARY MINUS FURLOUGHS":"$82878.00"},{"NAME":"ALEXE, ELENA","JOB TITLE":"POLICE OFFICER","DEPARTMENT":"POLICE","EMPLOYEE ANNUAL SALARY":"$79926.00","ESTIMATED ANNUAL SALARY MINUS FURLOUGHS":"$79926.00"},{"NAME":"ALFARO JR, BERNARDO","JOB TITLE":"AVIATION SECURITY OFFICER","DEPARTMENT":"AVIATION","EMPLOYEE ANNUAL SALARY":"$64596.00","ESTIMATED ANNUAL SALARY MINUS FURLOUGHS":"$61874.00"},{"NAME":"ALFARO, HECTOR","JOB TITLE":"POLICE OFFICER","DEPARTMENT":"POLICE","EMPLOYEE ANNUAL SALARY":"$79926.00","ESTIMATED ANNUAL SALARY MINUS FURLOUGHS":"$79926.00"},{"NAME":"ALFARO, JOSEPH S","JOB TITLE":"POLICE OFFICER","DEPARTMENT":"POLICE","EMPLOYEE ANNUAL SALARY":"$77238.00","ESTIMATED ANNUAL SALARY MINUS FURLOUGHS":"$77238.00"},{"NAME":"ALFARO, JOSEPHJAM S","JOB TITLE":"POLICE OFFICER","DEPARTMENT":"POLICE","EMPLOYEE ANNUAL SALARY":"$71040.00","ESTIMATED ANNUAL SALARY MINUS FURLOUGHS":"$71040.00"},{"NAME":"ALFARO, MARTHA","JOB TITLE":"PUBLIC HEALTH NURSE I","DEPARTMENT":"HEALTH","EMPLOYEE ANNUAL SALARY":"$56496.00","ESTIMATED ANNUAL SALARY MINUS FURLOUGHS":"$56496.00"},{"NAME":"ALFERES, GERARDO F","JOB TITLE":"SUPERVISING VIDEOGRAPHER","DEPARTMENT":"BUSINESS AFFAIRS","EMPLOYEE ANNUAL SALARY":"$73752.00","ESTIMATED ANNUAL SALARY MINUS FURLOUGHS":"$66970.00"},{"NAME":"ALFICH, FRED T","JOB TITLE":"HOISTING ENGINEER","DEPARTMENT":"WATER MGMNT","EMPLOYEE ANNUAL SALARY":"$93808.00","ESTIMATED ANNUAL SALARY MINUS FURLOUGHS":"$85541.00"},{"NAME":"ALFICH, SCOTT","JOB TITLE":"HOISTING ENGINEER","DEPARTMENT":"TRANSPORTN","EMPLOYEE ANNUAL SALARY":"$93808.00","ESTIMATED ANNUAL SALARY MINUS FURLOUGHS":"$85541.00"},{"NAME":"ALFIERI, NICHOLAS A","JOB TITLE":"TITLE V PROGRAM TRAINEE I","DEPARTMENT":"FAMILY & SUPPORT","EMPLOYEE ANNUAL SALARY":"$8580.00","ESTIMATED ANNUAL SALARY MINUS FURLOUGHS":"$8580.00"},{"NAME":"ALFINI, PAUL R","JOB TITLE":"POLICE OFFICER","DEPARTMENT":"POLICE","EMPLOYEE ANNUAL SALARY":"$89646.00","ESTIMATED ANNUAL SALARY MINUS FURLOUGHS":"$89646.00"},{"NAME":"ALFONSO, MATTHEW N","JOB TITLE":"SCHEDULER","DEPARTMENT":"MAYOR'S OFFICE","EMPLOYEE ANNUAL SALARY":"$40008.00","ESTIMATED ANNUAL SALARY MINUS FURLOUGHS":"$36329.00"},{"NAME":"ALFORD, LINDA D","JOB TITLE":"CROSSING GUARD","DEPARTMENT":"POLICE","EMPLOYEE ANNUAL SALARY":"$15319.00","ESTIMATED ANNUAL SALARY MINUS FURLOUGHS":"$15319.00"},{"NAME":"ALFRED, BRENDA L","JOB TITLE":"WARD CLERK","DEPARTMENT":"STREETS & SAN","EMPLOYEE ANNUAL SALARY":"$53340.00","ESTIMATED ANNUAL SALARY MINUS FURLOUGHS":"$48640.00"},{"NAME":"ALFRED, JANICE M","JOB TITLE":"HEAD LIBRARY CLERK","DEPARTMENT":"PUBLIC LIBRARY","EMPLOYEE ANNUAL SALARY":"$61308.00","ESTIMATED ANNUAL SALARY MINUS FURLOUGHS":"$61308.00"},{"NAME":"ALFRED, MYRTA T","JOB TITLE":"POLICE OFFICER","DEPARTMENT":"POLICE","EMPLOYEE ANNUAL SALARY":"$79926.00","ESTIMATED ANNUAL SALARY MINUS FURLOUGHS":"$79926.00"},{"NAME":"ALFRED, SANDRA L","JOB TITLE":"DEPUTY DIR","DEPARTMENT":"ANIMAL CONTRL","EMPLOYEE ANNUAL SALARY":"$80904.00","ESTIMATED ANNUAL SALARY MINUS FURLOUGHS":"$73465.00"},{"NAME":"ALGAS, JONATHAN T","JOB TITLE":"FIREFIGHTER-EMT","DEPARTMENT":"FIRE","EMPLOYEE ANNUAL SALARY":"$78354.00","ESTIMATED ANNUAL SALARY MINUS FURLOUGHS":"$78354.00"},{"NAME":"ALGHINI, LISA M","JOB TITLE":"POLICE OFFICER","DEPARTMENT":"POLICE","EMPLOYEE ANNUAL SALARY":"$74628.00","ESTIMATED ANNUAL SALARY MINUS FURLOUGHS":"$74628.00"},{"NAME":"ALGHINI, RICHARD","JOB TITLE":"POLICE OFFICER","DEPARTMENT":"POLICE","EMPLOYEE ANNUAL SALARY":"$74628.00","ESTIMATED ANNUAL SALARY MINUS FURLOUGHS":"$74628.00"},{"NAME":"ALI KELLEY, YASMINE M","JOB TITLE":"MANAGER OF POLICE PAYROLLS","DEPARTMENT":"POLICE","EMPLOYEE ANNUAL SALARY":"$97728.00","ESTIMATED ANNUAL SALARY MINUS FURLOUGHS":"$88742.00"},{"NAME":"ALI, BILAL R","JOB TITLE":"POLICE OFFICER","DEPARTMENT":"POLICE","EMPLOYEE ANNUAL SALARY":"$77238.00","ESTIMATED ANNUAL SALARY MINUS FURLOUGHS":"$77238.00"},{"NAME":"ALI, FARI","JOB TITLE":"SANITATION LABORER","DEPARTMENT":"STREETS & SAN","EMPLOYEE ANNUAL SALARY":"$65894.00","ESTIMATED ANNUAL SALARY MINUS FURLOUGHS":"$60088.00"},{"NAME":"ALI, JAVED","JOB TITLE":"POLICE OFFICER","DEPARTMENT":"POLICE","EMPLOYEE ANNUAL SALARY":"$71040.00","ESTIMATED ANNUAL SALARY MINUS FURLOUGHS":"$71040.00"},{"NAME":"ALI, MEER I","JOB TITLE":"POLICE OFFICER","DEPARTMENT":"POLICE","EMPLOYEE ANNUAL SALARY":"$79926.00","ESTIMATED ANNUAL SALARY MINUS FURLOUGHS":"$79926.00"},{"NAME":"ALI, MOHAMMED","JOB TITLE":"POLICE OFFICER","DEPARTMENT":"POLICE","EMPLOYEE ANNUAL SALARY":"$74628.00","ESTIMATED ANNUAL SALARY MINUS FURLOUGHS":"$74628.00"},{"NAME":"ALI, NAYYIRAH","JOB TITLE":"TRAFFIC CONTROL AIDE-HOURLY","DEPARTMENT":"OEMC","EMPLOYEE ANNUAL SALARY":"$18886.00","ESTIMATED ANNUAL SALARY MINUS FURLOUGHS":"$18886.00"},{"NAME":"ALI, SYED H","JOB TITLE":"CONSTRUCTION LABORER","DEPARTMENT":"WATER MGMNT","EMPLOYEE ANNUAL SALARY":"$73216.00","ESTIMATED ANNUAL SALARY MINUS FURLOUGHS":"$66764.00"},{"NAME":"ALIASI, ERMINIO","JOB TITLE":"CONSTRUCTION LABORER","DEPARTMENT":"WATER MGMNT","EMPLOYEE ANNUAL SALARY":"$73216.00","ESTIMATED ANNUAL SALARY MINUS FURLOUGHS":"$66764.00"},{"NAME":"ALICEA JR, FELIX","JOB TITLE":"LABORER","DEPARTMENT":"AVIATION","EMPLOYEE ANNUAL SALARY":"$61506.00","ESTIMATED ANNUAL SALARY MINUS FURLOUGHS":"$56086.00"},{"NAME":"ALICEA, ANGEL R","JOB TITLE":"OPERATING ENGINEER-GROUP C","DEPARTMENT":"AVIATION","EMPLOYEE ANNUAL SALARY":"$82638.00","ESTIMATED ANNUAL SALARY MINUS FURLOUGHS":"$75356.00"},{"NAME":"ALICEA, JOSE L","JOB TITLE":"MOTOR TRUCK DRIVER","DEPARTMENT":"TRANSPORTN","EMPLOYEE ANNUAL SALARY":"$70408.00","ESTIMATED ANNUAL SALARY MINUS FURLOUGHS":"$70408.00"},{"NAME":"ALICEA, VILMA R","JOB TITLE":"COMMUNICABLE DISEASE CONTROL INVESTIGATOR II","DEPARTMENT":"HEALTH","EMPLOYEE ANNUAL SALARY":"$55872.00","ESTIMATED ANNUAL SALARY MINUS FURLOUGHS":"$55872.00"},{"NAME":"ALICEA, WILLIAM N","JOB TITLE":"GENERAL FOREMAN OF GENERAL TRADES","DEPARTMENT":"GENERAL SERVICES","EMPLOYEE ANNUAL SALARY":"$104562.00","ESTIMATED ANNUAL SALARY MINUS FURLOUGHS":"$95347.00"},{"NAME":"ALICEA-REYES, CARMEN E","JOB TITLE":"DEPUTY COMMISSIONER","DEPARTMENT":"FAMILY & SUPPORT","EMPLOYEE ANNUAL SALARY":"$105828.00","ESTIMATED ANNUAL SALARY MINUS FURLOUGHS":"$96097.00"},{"NAME":"ALIKHAN, VICTORIA","JOB TITLE":"LIBRARY ASSOCIATE","DEPARTMENT":"PUBLIC LIBRARY","EMPLOYEE ANNUAL SALARY":"$60792.00","ESTIMATED ANNUAL SALARY MINUS FURLOUGHS":"$60792.00"},{"NAME":"ALINOVICH, PETER A","JOB TITLE":"OPERATING ENGINEER-GROUP A","DEPARTMENT":"GENERAL SERVICES","EMPLOYEE ANNUAL SALARY":"$86986.00","ESTIMATED ANNUAL SALARY MINUS FURLOUGHS":"$79320.00"},{"NAME":"ALIOTO, ROCCO J","JOB TITLE":"POLICE OFFICER","DEPARTMENT":"POLICE","EMPLOYEE ANNUAL SALARY":"$77238.00","ESTIMATED ANNUAL SALARY MINUS FURLOUGHS":"$77238.00"},{"NAME":"ALLAIN, CAROLYN","JOB TITLE":"TELEPHONE EQUIPMENT COORD","DEPARTMENT":"DoIT","EMPLOYEE ANNUAL SALARY":"$64248.00","ESTIMATED ANNUAL SALARY MINUS FURLOUGHS":"$64248.00"},{"NAME":"ALLAN, ANTHONY","JOB TITLE":"GRANTS RESEARCH SPECIALIST","DEPARTMENT":"FAMILY & SUPPORT","EMPLOYEE ANNUAL SALARY":"$76536.00","ESTIMATED ANNUAL SALARY MINUS FURLOUGHS":"$76536.00"},{"NAME":"ALLAN, JOHN S","JOB TITLE":"POLICE OFFICER","DEPARTMENT":"POLICE","EMPLOYEE ANNUAL SALARY":"$86508.00","ESTIMATED ANNUAL SALARY MINUS FURLOUGHS":"$86508.00"},{"NAME":"ALLEGRETTI, ANTHONY","JOB TITLE":"FIRE ENGINEER-EMT","DEPARTMENT":"FIRE","EMPLOYEE ANNUAL SALARY":"$96870.00","ESTIMATED ANNUAL SALARY MINUS FURLOUGHS":"$96870.00"},{"NAME":"ALLEMAN, ROBERT R","JOB TITLE":"OPERATING ENGINEER-GROUP A","DEPARTMENT":"WATER MGMNT","EMPLOYEE ANNUAL SALARY":"$86986.00","ESTIMATED ANNUAL SALARY MINUS FURLOUGHS":"$79320.00"},{"NAME":"ALLEN BROWN, CORA I","JOB TITLE":"CUSTOMER ACCOUNT REPRESENTATIVE","DEPARTMENT":"REVENUE","EMPLOYEE ANNUAL SALARY":"$55872.00","ESTIMATED ANNUAL SALARY MINUS FURLOUGHS":"$55872.00"},{"NAME":"ALLEN JR, ISAAC","JOB TITLE":"POOL MOTOR TRUCK DRIVER","DEPARTMENT":"STREETS & SAN","EMPLOYEE ANNUAL SALARY":"$70408.00","ESTIMATED ANNUAL SALARY MINUS FURLOUGHS":"$70408.00"},{"NAME":"ALLEN JR, PERCY J","JOB TITLE":"POLICE OFFICER","DEPARTMENT":"POLICE","EMPLOYEE ANNUAL SALARY":"$87048.00","ESTIMATED ANNUAL SALARY MINUS FURLOUGHS":"$87048.00"},{"NAME":"ALLEN, ALFRED L","JOB TITLE":"FIRE ENGINEER-EMT","DEPARTMENT":"FIRE","EMPLOYEE ANNUAL SALARY":"$94134.00","ESTIMATED ANNUAL SALARY MINUS FURLOUGHS":"$94134.00"},{"NAME":"ALLEN, ALPHONSO J","JOB TITLE":"PARAMEDIC","DEPARTMENT":"FIRE","EMPLOYEE ANNUAL SALARY":"$74628.00","ESTIMATED ANNUAL SALARY MINUS FURLOUGHS":"$74628.00"},{"NAME":"ALLEN, ANDRE G","JOB TITLE":"FIREFIGHTER","DEPARTMENT":"FIRE","EMPLOYEE ANNUAL SALARY":"$79926.00","ESTIMATED ANNUAL SALARY MINUS FURLOUGHS":"$79926.00"},{"NAME":"ALLEN, ANNETTE D","JOB TITLE":"CLERK IV","DEPARTMENT":"POLICE","EMPLOYEE ANNUAL SALARY":"$50952.00","ESTIMATED ANNUAL SALARY MINUS FURLOUGHS":"$50952.00"},{"NAME":"ALLEN, ANTONIO W","JOB TITLE":"EXPLOSIVES TECHNICIAN I","DEPARTMENT":"POLICE","EMPLOYEE ANNUAL SALARY":"$95694.00","ESTIMATED ANNUAL SALARY MINUS FURLOUGHS":"$95694.00"},{"NAME":"ALLEN, CHRISTOPHER W","JOB TITLE":"TRAFFIC CONTROL AIDE-HOURLY","DEPARTMENT":"OEMC","EMPLOYEE ANNUAL SALARY":"$18886.00","ESTIMATED ANNUAL SALARY MINUS FURLOUGHS":"$18886.00"},{"NAME":"ALLEN, CLINTON S","JOB TITLE":"DISABILITY SPECIALIST II","DEPARTMENT":"DISABILITIES","EMPLOYEE ANNUAL SALARY":"$73932.00","ESTIMATED ANNUAL SALARY MINUS FURLOUGHS":"$73932.00"},{"NAME":"ALLEN, CRAIG M","JOB TITLE":"FIRE ENGINEER-EMT","DEPARTMENT":"FIRE","EMPLOYEE ANNUAL SALARY":"$90834.00","ESTIMATED ANNUAL SALARY MINUS FURLOUGHS":"$90834.00"},{"NAME":"ALLEN, DANIEL H","JOB TITLE":"SERGEANT","DEPARTMENT":"POLICE","EMPLOYEE ANNUAL SALARY":"$95694.00","ESTIMATED ANNUAL SALARY MINUS FURLOUGHS":"$95694.00"},{"NAME":"ALLEN, DANIEL J","JOB TITLE":"FIREFIGHTER","DEPARTMENT":"FIRE","EMPLOYEE ANNUAL SALARY":"$79926.00","ESTIMATED ANNUAL SALARY MINUS FURLOUGHS":"$79926.00"},{"NAME":"ALLEN, DANIEL P","JOB TITLE":"CHIEF ELECTRICAL INSPECTOR","DEPARTMENT":"BUILDINGS","EMPLOYEE ANNUAL SALARY":"$106884.00","ESTIMATED ANNUAL SALARY MINUS FURLOUGHS":"$97056.00"},{"NAME":"ALLEN, DAVID","JOB TITLE":"POLICE OFFICER","DEPARTMENT":"POLICE","EMPLOYEE ANNUAL SALARY":"$74628.00","ESTIMATED ANNUAL SALARY MINUS FURLOUGHS":"$74628.00"},{"NAME":"ALLEN, DEBORAH A","JOB TITLE":"POLICE OFFICER","DEPARTMENT":"POLICE","EMPLOYEE ANNUAL SALARY":"$79926.00","ESTIMATED ANNUAL SALARY MINUS FURLOUGHS":"$79926.00"},{"NAME":"ALLEN, DENISE A","JOB TITLE":"SENIOR LIBRARY CLERK","DEPARTMENT":"PUBLIC LIBRARY","EMPLOYEE ANNUAL SALARY":"$50952.00","ESTIMATED ANNUAL SALARY MINUS FURLOUGHS":"$50952.00"},{"NAME":"ALLEN, DENOTRA","JOB TITLE":"POLICE OFFICER","DEPARTMENT":"POLICE","EMPLOYEE ANNUAL SALARY":"$79926.00","ESTIMATED ANNUAL SALARY MINUS FURLOUGHS":"$79926.00"},{"NAME":"ALLEN, DERRICK D","JOB TITLE":"POLICE AGENT","DEPARTMENT":"POLICE","EMPLOYEE ANNUAL SALARY":"$83916.00","ESTIMATED ANNUAL SALARY MINUS FURLOUGHS":"$83916.00"},{"NAME":"ALLEN, DOROTHY M","JOB TITLE":"CROSSING GUARD","DEPARTMENT":"POLICE","EMPLOYEE ANNUAL SALARY":"$15319.00","ESTIMATED ANNUAL SALARY MINUS FURLOUGHS":"$15319.00"},{"NAME":"ALLEN, DWIGHT","JOB TITLE":"SANITATION LABORER","DEPARTMENT":"STREETS & SAN","EMPLOYEE ANNUAL SALARY":"$65894.00","ESTIMATED ANNUAL SALARY MINUS FURLOUGHS":"$60088.00"},{"NAME":"ALLEN, ELIZABETH","JOB TITLE":"ACCOUNTANT I","DEPARTMENT":"TREASURER","EMPLOYEE ANNUAL SALARY":"$66960.00","ESTIMATED ANNUAL SALARY MINUS FURLOUGHS":"$66960.00"},{"NAME":"ALLEN, GLORIA","JOB TITLE":"POLICE OFFICER","DEPARTMENT":"POLICE","EMPLOYEE ANNUAL SALARY":"$82878.00","ESTIMATED ANNUAL SALARY MINUS FURLOUGHS":"$82878.00"},{"NAME":"ALLEN, GORDON K","JOB TITLE":"POLICE OFFICER","DEPARTMENT":"POLICE","EMPLOYEE ANNUAL SALARY":"$79926.00","ESTIMATED ANNUAL SALARY MINUS FURLOUGHS":"$79926.00"},{"NAME":"ALLEN, HENRY C","JOB TITLE":"POLICE OFFICER","DEPARTMENT":"POLICE","EMPLOYEE ANNUAL SALARY":"$77238.00","ESTIMATED ANNUAL SALARY MINUS FURLOUGHS":"$77238.00"},{"NAME":"ALLEN, JAMES W","JOB TITLE":"POLICE OFFICER","DEPARTMENT":"POLICE","EMPLOYEE ANNUAL SALARY":"$74628.00","ESTIMATED ANNUAL SALARY MINUS FURLOUGHS":"$74628.00"},{"NAME":"ALLEN, JEFFREY W","JOB TITLE":"SERGEANT","DEPARTMENT":"POLICE","EMPLOYEE ANNUAL SALARY":"$98766.00","ESTIMATED ANNUAL SALARY MINUS FURLOUGHS":"$98766.00"},{"NAME":"ALLEN, JOAN D","JOB TITLE":"POLICE COMMUNICATIONS OPERATOR I","DEPARTMENT":"OEMC","EMPLOYEE ANNUAL SALARY":"$61692.00","ESTIMATED ANNUAL SALARY MINUS FURLOUGHS":"$59092.00"},{"NAME":"ALLEN, JONATHAN E","JOB TITLE":"STAFF ASST","DEPARTMENT":"FINANCE","EMPLOYEE ANNUAL SALARY":"$67224.00","ESTIMATED ANNUAL SALARY MINUS FURLOUGHS":"$61042.00"},{"NAME":"ALLEN, KEITH A","JOB TITLE":"POLICE OFFICER","DEPARTMENT":"POLICE","EMPLOYEE ANNUAL SALARY":"$86508.00","ESTIMATED ANNUAL SALARY MINUS FURLOUGHS":"$86508.00"},{"NAME":"ALLEN, KEVIN C","JOB TITLE":"POLICE OFFICER","DEPARTMENT":"POLICE","EMPLOYEE ANNUAL SALARY":"$82878.00","ESTIMATED ANNUAL SALARY MINUS FURLOUGHS":"$82878.00"},{"NAME":"ALLEN, KEVIN M","JOB TITLE":"ACCOUNTANT III","DEPARTMENT":"FINANCE","EMPLOYEE ANNUAL SALARY":"$73200.00","ESTIMATED ANNUAL SALARY MINUS FURLOUGHS":"$73200.00"},{"NAME":"ALLEN, LA SHAWNDA","JOB TITLE":"COLLECTIONS REPRESENTATIVE","DEPARTMENT":"REVENUE","EMPLOYEE ANNUAL SALARY":"$48576.00","ESTIMATED ANNUAL SALARY MINUS FURLOUGHS":"$48576.00"},{"NAME":"ALLEN, LAJEUNE R","JOB TITLE":"POLICE OFFICER","DEPARTMENT":"POLICE","EMPLOYEE ANNUAL SALARY":"$82878.00","ESTIMATED ANNUAL SALARY MINUS FURLOUGHS":"$82878.00"},{"NAME":"ALLEN, LAQUETIA L","JOB TITLE":"TRAFFIC CONTROL AIDE","DEPARTMENT":"OEMC","EMPLOYEE ANNUAL SALARY":"$51216.00","ESTIMATED ANNUAL SALARY MINUS FURLOUGHS":"$49057.00"},{"NAME":"ALLEN, MARIE","JOB TITLE":"CROSSING GUARD","DEPARTMENT":"POLICE","EMPLOYEE ANNUAL SALARY":"$21268.00","ESTIMATED ANNUAL SALARY MINUS FURLOUGHS":"$21268.00"},{"NAME":"ALLEN, MARIE L","JOB TITLE":"SENIOR DATA ENTRY OPERATOR","DEPARTMENT":"POLICE","EMPLOYEE ANNUAL SALARY":"$55872.00","ESTIMATED ANNUAL SALARY MINUS FURLOUGHS":"$55872.00"},{"NAME":"ALLEN, MARK D","JOB TITLE":"POLICE OFFICER","DEPARTMENT":"POLICE","EMPLOYEE ANNUAL SALARY":"$87048.00","ESTIMATED ANNUAL SALARY MINUS FURLOUGHS":"$87048.00"},{"NAME":"ALLEN, MELVIN","JOB TITLE":"SANITATION LABORER","DEPARTMENT":"STREETS & SAN","EMPLOYEE ANNUAL SALARY":"$65894.00","ESTIMATED ANNUAL SALARY MINUS FURLOUGHS":"$60088.00"},{"NAME":"ALLEN, MICHAEL J","JOB TITLE":"PARAMEDIC","DEPARTMENT":"FIRE","EMPLOYEE ANNUAL SALARY":"$67704.00","ESTIMATED ANNUAL SALARY MINUS FURLOUGHS":"$67704.00"},{"NAME":"ALLEN, MYRA B","JOB TITLE":"CROSSING GUARD","DEPARTMENT":"POLICE","EMPLOYEE ANNUAL SALARY":"$16047.00","ESTIMATED ANNUAL SALARY MINUS FURLOUGHS":"$16047.00"},{"NAME":"ALLEN, NAJJA T","JOB TITLE":"LIBRARY CLERK - HOURLY","DEPARTMENT":"PUBLIC LIBRARY","EMPLOYEE ANNUAL SALARY":"$14706.00","ESTIMATED ANNUAL SALARY MINUS FURLOUGHS":"$14706.00"},{"NAME":"ALLEN, PETER B","JOB TITLE":"BRIDGE OPERATOR","DEPARTMENT":"TRANSPORTN","EMPLOYEE ANNUAL SALARY":"$55872.00","ESTIMATED ANNUAL SALARY MINUS FURLOUGHS":"$50948.00"},{"NAME":"ALLEN, PHOEBE","JOB TITLE":"POLICE OFFICER","DEPARTMENT":"POLICE","EMPLOYEE ANNUAL SALARY":"$74628.00","ESTIMATED ANNUAL SALARY MINUS FURLOUGHS":"$74628.00"},{"NAME":"ALLEN, RAYMOND G","JOB TITLE":"POLICE OFFICER","DEPARTMENT":"POLICE","EMPLOYEE ANNUAL SALARY":"$79926.00","ESTIMATED ANNUAL SALARY MINUS FURLOUGHS":"$79926.00"},{"NAME":"ALLEN, REGAN J","JOB TITLE":"POLICE OFFICER","DEPARTMENT":"POLICE","EMPLOYEE ANNUAL SALARY":"$74628.00","ESTIMATED ANNUAL SALARY MINUS FURLOUGHS":"$74628.00"},{"NAME":"ALLEN, RICHARD","JOB TITLE":"POOL MOTOR TRUCK DRIVER","DEPARTMENT":"STREETS & SAN","EMPLOYEE ANNUAL SALARY":"$70408.00","ESTIMATED ANNUAL SALARY MINUS FURLOUGHS":"$70408.00"},{"NAME":"ALLEN, ROBERT","JOB TITLE":"MACHINIST","DEPARTMENT":"WATER MGMNT","EMPLOYEE ANNUAL SALARY":"$89773.00","ESTIMATED ANNUAL SALARY MINUS FURLOUGHS":"$81862.00"},{"NAME":"ALLEN, ROBERT G","JOB TITLE":"POOL MOTOR TRUCK DRIVER","DEPARTMENT":"STREETS & SAN","EMPLOYEE ANNUAL SALARY":"$17602.00","ESTIMATED ANNUAL SALARY MINUS FURLOUGHS":"$17602.00"},{"NAME":"ALLEN, ROBERT L","JOB TITLE":"MOTOR TRUCK DRIVER","DEPARTMENT":"STREETS & SAN","EMPLOYEE ANNUAL SALARY":"$70408.00","ESTIMATED ANNUAL SALARY MINUS FURLOUGHS":"$70408.00"},{"NAME":"ALLEN, RUTH B","JOB TITLE":"CIVIL ENGINEER III","DEPARTMENT":"WATER MGMNT","EMPLOYEE ANNUAL SALARY":"$88140.00","ESTIMATED ANNUAL SALARY MINUS FURLOUGHS":"$88140.00"},{"NAME":"ALLEN, RYAN M","JOB TITLE":"LIBRARY CLERK","DEPARTMENT":"PUBLIC LIBRARY","EMPLOYEE ANNUAL SALARY":"$36780.00","ESTIMATED ANNUAL SALARY MINUS FURLOUGHS":"$36780.00"},{"NAME":"ALLEN, RYSHON C","JOB TITLE":"LABORER","DEPARTMENT":"AVIATION","EMPLOYEE ANNUAL SALARY":"$61506.00","ESTIMATED ANNUAL SALARY MINUS FURLOUGHS":"$56086.00"},{"NAME":"ALLEN, SANDRA","JOB TITLE":"ADMINISTRATIVE ASST II","DEPARTMENT":"BUILDINGS","EMPLOYEE ANNUAL SALARY":"$55872.00","ESTIMATED ANNUAL SALARY MINUS FURLOUGHS":"$55872.00"},{"NAME":"ALLEN, STEVEN R","JOB TITLE":"MACHINIST","DEPARTMENT":"FLEET MANAGEMNT","EMPLOYEE ANNUAL SALARY":"$89773.00","ESTIMATED ANNUAL SALARY MINUS FURLOUGHS":"$81862.00"},{"NAME":"ALLEN, TERRY L","JOB TITLE":"FOREMAN OF CONSTRUCTION LABORERS","DEPARTMENT":"TRANSPORTN","EMPLOYEE ANNUAL SALARY":"$75504.00","ESTIMATED ANNUAL SALARY MINUS FURLOUGHS":"$68850.00"},{"NAME":"ALLEN, TIMOTHY","JOB TITLE":"SANITATION LABORER","DEPARTMENT":"STREETS & SAN","EMPLOYEE ANNUAL SALARY":"$65894.00","ESTIMATED ANNUAL SALARY MINUS FURLOUGHS":"$60088.00"},{"NAME":"ALLEN, TIMOTHY M","JOB TITLE":"ANIMAL CONTROL OFFICER","DEPARTMENT":"ANIMAL CONTRL","EMPLOYEE ANNUAL SALARY":"$64596.00","ESTIMATED ANNUAL SALARY MINUS FURLOUGHS":"$61874.00"},{"NAME":"ALLEN, TYREE D","JOB TITLE":"SANITATION LABORER","DEPARTMENT":"STREETS & SAN","EMPLOYEE ANNUAL SALARY":"$52707.00","ESTIMATED ANNUAL SALARY MINUS FURLOUGHS":"$48063.00"},{"NAME":"ALLEN, VERDIE P","JOB TITLE":"AMBULANCE COMMANDER","DEPARTMENT":"FIRE","EMPLOYEE ANNUAL SALARY":"$114498.00","ESTIMATED ANNUAL SALARY MINUS FURLOUGHS":"$114498.00"},{"NAME":"ALLEN, VINCENT","JOB TITLE":"POLICE OFFICER","DEPARTMENT":"POLICE","EMPLOYEE ANNUAL SALARY":"$83916.00","ESTIMATED ANNUAL SALARY MINUS FURLOUGHS":"$83916.00"},{"NAME":"ALLEN, WANDA L","JOB TITLE":"ADMINISTRATIVE ASST III","DEPARTMENT":"PUBLIC LIBRARY","EMPLOYEE ANNUAL SALARY":"$64248.00","ESTIMATED ANNUAL SALARY MINUS FURLOUGHS":"$64248.00"},{"NAME":"ALLEN, WILLIAM L","JOB TITLE":"SANITATION LABORER","DEPARTMENT":"STREETS & SAN","EMPLOYEE ANNUAL SALARY":"$65894.00","ESTIMATED ANNUAL SALARY MINUS FURLOUGHS":"$60088.00"},{"NAME":"ALLENSON, SAGE","JOB TITLE":"POLICE OFFICER","DEPARTMENT":"POLICE","EMPLOYEE ANNUAL SALARY":"$67704.00","ESTIMATED ANNUAL SALARY MINUS FURLOUGHS":"$67704.00"},{"NAME":"ALLEYNE, HATTIE","JOB TITLE":"POOL MOTOR TRUCK DRIVER","DEPARTMENT":"STREETS & SAN","EMPLOYEE ANNUAL SALARY":"$70408.00","ESTIMATED ANNUAL SALARY MINUS FURLOUGHS":"$70408.00"},{"NAME":"ALLEYNE, STEVE C","JOB TITLE":"FIRE ENGINEER-EMT","DEPARTMENT":"FIRE","EMPLOYEE ANNUAL SALARY":"$87756.00","ESTIMATED ANNUAL SALARY MINUS FURLOUGHS":"$87756.00"},{"NAME":"ALLISON, ALLYSON M","JOB TITLE":"STAFF ASST TO THE ALDERMAN","DEPARTMENT":"CITY COUNCIL","EMPLOYEE ANNUAL SALARY":"$51696.00","ESTIMATED ANNUAL SALARY MINUS FURLOUGHS":"$46942.00"},{"NAME":"ALLISON, JOHN L","JOB TITLE":"ANIMAL CONTROL OFFICER","DEPARTMENT":"ANIMAL CONTRL","EMPLOYEE ANNUAL SALARY":"$53628.00","ESTIMATED ANNUAL SALARY MINUS FURLOUGHS":"$51368.00"}]}